Workbook

Sheet Podsumowanie
A1: Verris — parytet funkcji wobec rynku
A2: Wygenerowane 2026-10-13 z audyt/dane/macierz.csv · nie edytuj tego pliku ręcznie
A4: Werdykt parytetu
A5: Wartość | B5: Pozycji
A6: PARYTET | B6: =COUNTIF(Macierz!$K$2:$K$441,A6)
A7: PRZEWAGA | B7: =COUNTIF(Macierz!$K$2:$K$441,A7)
A8: CZĘŚCIOWY | B8: =COUNTIF(Macierz!$K$2:$K$441,A8)
A9: LUKA | B9: =COUNTIF(Macierz!$K$2:$K$441,A9)
A10: POZA ZAKRESEM | B10: =COUNTIF(Macierz!$K$2:$K$441,A10)
A13: Stan implementacji
A14: Wartość | B14: Pozycji
A15: DZIAŁA | B15: =COUNTIF(Macierz!$I$2:$I$441,A15)
A16: CZĘŚCIOWE | B16: =COUNTIF(Macierz!$I$2:$I$441,A16)
A17: FLAGA | B17: =COUNTIF(Macierz!$I$2:$I$441,A17)
A18: ATRAPA | B18: =COUNTIF(Macierz!$I$2:$I$441,A18)
A19: ENDPOINT BEZ UI | B19: =COUNTIF(Macierz!$I$2:$I$441,A19)
A20: BRAK | B20: =COUNTIF(Macierz!$I$2:$I$441,A20)
A21: b.d. | B21: =COUNTIF(Macierz!$I$2:$I$441,A21)
A24: Krytyczność luk
A25: Wartość | B25: Pozycji
A26: BLOKER STARTU | B26: =COUNTIF(Macierz!$L$2:$L$441,A26)
A27: WYSOKA | B27: =COUNTIF(Macierz!$L$2:$L$441,A27)
A28: ŚREDNIA | B28: =COUNTIF(Macierz!$L$2:$L$441,A28)
A29: NISKA | B29: =COUNTIF(Macierz!$L$2:$L$441,A29)
A31: Pokrycie per kategoria
A32: Kategoria | B32: Pozycji | C32: Parytet+Przewaga | D32: Luki | E32: Blokery | F32: Pokrycie
A33: A — Domeny i konta | B33: =COUNTIF(Macierz!$B$2:$B$441,"A") | C33: =COUNTIFS(Macierz!$B$2:$B$441,"A",Macierz!$K$2:$K$441,"PARYTET")+COUNTIFS(Macierz!$B$2:$B$441,"A",Macierz!$K$2:$K$441,"PRZEWAGA") | D33: =COUNTIFS(Macierz!$B$2:$B$441,"A",Macierz!$K$2:$K$441,"LUKA") | E33: =COUNTIFS(Macierz!$B$2:$B$441,"A",Macierz!$L$2:$L$441,"BLOKER STARTU") | F33: =IFERROR(C33/B33,0)
A34: B — Runtime WWW | B34: =COUNTIF(Macierz!$B$2:$B$441,"B") | C34: =COUNTIFS(Macierz!$B$2:$B$441,"B",Macierz!$K$2:$K$441,"PARYTET")+COUNTIFS(Macierz!$B$2:$B$441,"B",Macierz!$K$2:$K$441,"PRZEWAGA") | D34: =COUNTIFS(Macierz!$B$2:$B$441,"B",Macierz!$K$2:$K$441,"LUKA") | E34: =COUNTIFS(Macierz!$B$2:$B$441,"B",Macierz!$L$2:$L$441,"BLOKER STARTU") | F34: =IFERROR(C34/B34,0)
A35: C — Pliki, FTP, SSH, Git | B35: =COUNTIF(Macierz!$B$2:$B$441,"C") | C35: =COUNTIFS(Macierz!$B$2:$B$441,"C",Macierz!$K$2:$K$441,"PARYTET")+COUNTIFS(Macierz!$B$2:$B$441,"C",Macierz!$K$2:$K$441,"PRZEWAGA") | D35: =COUNTIFS(Macierz!$B$2:$B$441,"C",Macierz!$K$2:$K$441,"LUKA") | E35: =COUNTIFS(Macierz!$B$2:$B$441,"C",Macierz!$L$2:$L$441,"BLOKER STARTU") | F35: =IFERROR(C35/B35,0)
A36: D — Bazy danych | B36: =COUNTIF(Macierz!$B$2:$B$441,"D") | C36: =COUNTIFS(Macierz!$B$2:$B$441,"D",Macierz!$K$2:$K$441,"PARYTET")+COUNTIFS(Macierz!$B$2:$B$441,"D",Macierz!$K$2:$K$441,"PRZEWAGA") | D36: =COUNTIFS(Macierz!$B$2:$B$441,"D",Macierz!$K$2:$K$441,"LUKA") | E36: =COUNTIFS(Macierz!$B$2:$B$441,"D",Macierz!$L$2:$L$441,"BLOKER STARTU") | F36: =IFERROR(C36/B36,0)
A37: E — Poczta | B37: =COUNTIF(Macierz!$B$2:$B$441,"E") | C37: =COUNTIFS(Macierz!$B$2:$B$441,"E",Macierz!$K$2:$K$441,"PARYTET")+COUNTIFS(Macierz!$B$2:$B$441,"E",Macierz!$K$2:$K$441,"PRZEWAGA") | D37: =COUNTIFS(Macierz!$B$2:$B$441,"E",Macierz!$K$2:$K$441,"LUKA") | E37: =COUNTIFS(Macierz!$B$2:$B$441,"E",Macierz!$L$2:$L$441,"BLOKER STARTU") | F37: =IFERROR(C37/B37,0)
A38: F — DNS | B38: =COUNTIF(Macierz!$B$2:$B$441,"F") | C38: =COUNTIFS(Macierz!$B$2:$B$441,"F",Macierz!$K$2:$K$441,"PARYTET")+COUNTIFS(Macierz!$B$2:$B$441,"F",Macierz!$K$2:$K$441,"PRZEWAGA") | D38: =COUNTIFS(Macierz!$B$2:$B$441,"F",Macierz!$K$2:$K$441,"LUKA") | E38: =COUNTIFS(Macierz!$B$2:$B$441,"F",Macierz!$L$2:$L$441,"BLOKER STARTU") | F38: =IFERROR(C38/B38,0)
A39: G — SSL i bezpieczeństwo | B39: =COUNTIF(Macierz!$B$2:$B$441,"G") | C39: =COUNTIFS(Macierz!$B$2:$B$441,"G",Macierz!$K$2:$K$441,"PARYTET")+COUNTIFS(Macierz!$B$2:$B$441,"G",Macierz!$K$2:$K$441,"PRZEWAGA") | D39: =COUNTIFS(Macierz!$B$2:$B$441,"G",Macierz!$K$2:$K$441,"LUKA") | E39: =COUNTIFS(Macierz!$B$2:$B$441,"G",Macierz!$L$2:$L$441,"BLOKER STARTU") | F39: =IFERROR(C39/B39,0)
A40: H — Backup i odtwarzanie | B40: =COUNTIF(Macierz!$B$2:$B$441,"H") | C40: =COUNTIFS(Macierz!$B$2:$B$441,"H",Macierz!$K$2:$K$441,"PARYTET")+COUNTIFS(Macierz!$B$2:$B$441,"H",Macierz!$K$2:$K$441,"PRZEWAGA") | D40: =COUNTIFS(Macierz!$B$2:$B$441,"H",Macierz!$K$2:$K$441,"LUKA") | E40: =COUNTIFS(Macierz!$B$2:$B$441,"H",Macierz!$L$2:$L$441,"BLOKER STARTU") | F40: =IFERROR(C40/B40,0)
A41: I — Aplikacje i WordPress | B41: =COUNTIF(Macierz!$B$2:$B$441,"I") | C41: =COUNTIFS(Macierz!$B$2:$B$441,"I",Macierz!$K$2:$K$441,"PARYTET")+COUNTIFS(Macierz!$B$2:$B$441,"I",Macierz!$K$2:$K$441,"PRZEWAGA") | D41: =COUNTIFS(Macierz!$B$2:$B$441,"I",Macierz!$K$2:$K$441,"LUKA") | E41: =COUNTIFS(Macierz!$B$2:$B$441,"I",Macierz!$L$2:$L$441,"BLOKER STARTU") | F41: =IFERROR(C41/B41,0)
A42: J — Wydajność i cache | B42: =COUNTIF(Macierz!$B$2:$B$441,"J") | C42: =COUNTIFS(Macierz!$B$2:$B$441,"J",Macierz!$K$2:$K$441,"PARYTET")+COUNTIFS(Macierz!$B$2:$B$441,"J",Macierz!$K$2:$K$441,"PRZEWAGA") | D42: =COUNTIFS(Macierz!$B$2:$B$441,"J",Macierz!$K$2:$K$441,"LUKA") | E42: =COUNTIFS(Macierz!$B$2:$B$441,"J",Macierz!$L$2:$L$441,"BLOKER STARTU") | F42: =IFERROR(C42/B42,0)
A43: K — Statystyki, logi, limity | B43: =COUNTIF(Macierz!$B$2:$B$441,"K") | C43: =COUNTIFS(Macierz!$B$2:$B$441,"K",Macierz!$K$2:$K$441,"PARYTET")+COUNTIFS(Macierz!$B$2:$B$441,"K",Macierz!$K$2:$K$441,"PRZEWAGA") | D43: =COUNTIFS(Macierz!$B$2:$B$441,"K",Macierz!$K$2:$K$441,"LUKA") | E43: =COUNTIFS(Macierz!$B$2:$B$441,"K",Macierz!$L$2:$L$441,"BLOKER STARTU") | F43: =IFERROR(C43/B43,0)
A44: L — Automatyzacja | B44: =COUNTIF(Macierz!$B$2:$B$441,"L") | C44: =COUNTIFS(Macierz!$B$2:$B$441,"L",Macierz!$K$2:$K$441,"PARYTET")+COUNTIFS(Macierz!$B$2:$B$441,"L",Macierz!$K$2:$K$441,"PRZEWAGA") | D44: =COUNTIFS(Macierz!$B$2:$B$441,"L",Macierz!$K$2:$K$441,"LUKA") | E44: =COUNTIFS(Macierz!$B$2:$B$441,"L",Macierz!$L$2:$L$441,"BLOKER STARTU") | F44: =IFERROR(C44/B44,0)
A45: M — Rozliczenia | B45: =COUNTIF(Macierz!$B$2:$B$441,"M") | C45: =COUNTIFS(Macierz!$B$2:$B$441,"M",Macierz!$K$2:$K$441,"PARYTET")+COUNTIFS(Macierz!$B$2:$B$441,"M",Macierz!$K$2:$K$441,"PRZEWAGA") | D45: =COUNTIFS(Macierz!$B$2:$B$441,"M",Macierz!$K$2:$K$441,"LUKA") | E45: =COUNTIFS(Macierz!$B$2:$B$441,"M",Macierz!$L$2:$L$441,"BLOKER STARTU") | F45: =IFERROR(C45/B45,0)
A46: N — Wsparcie i ops | B46: =COUNTIF(Macierz!$B$2:$B$441,"N") | C46: =COUNTIFS(Macierz!$B$2:$B$441,"N",Macierz!$K$2:$K$441,"PARYTET")+COUNTIFS(Macierz!$B$2:$B$441,"N",Macierz!$K$2:$K$441,"PRZEWAGA") | D46: =COUNTIFS(Macierz!$B$2:$B$441,"N",Macierz!$K$2:$K$441,"LUKA") | E46: =COUNTIFS(Macierz!$B$2:$B$441,"N",Macierz!$L$2:$L$441,"BLOKER STARTU") | F46: =IFERROR(C46/B46,0)
A47: O — Multi-user i reseller | B47: =COUNTIF(Macierz!$B$2:$B$441,"O") | C47: =COUNTIFS(Macierz!$B$2:$B$441,"O",Macierz!$K$2:$K$441,"PARYTET")+COUNTIFS(Macierz!$B$2:$B$441,"O",Macierz!$K$2:$K$441,"PRZEWAGA") | D47: =COUNTIFS(Macierz!$B$2:$B$441,"O",Macierz!$K$2:$K$441,"LUKA") | E47: =COUNTIFS(Macierz!$B$2:$B$441,"O",Macierz!$L$2:$L$441,"BLOKER STARTU") | F47: =IFERROR(C47/B47,0)
A48: P — Zgodność | B48: =COUNTIF(Macierz!$B$2:$B$441,"P") | C48: =COUNTIFS(Macierz!$B$2:$B$441,"P",Macierz!$K$2:$K$441,"PARYTET")+COUNTIFS(Macierz!$B$2:$B$441,"P",Macierz!$K$2:$K$441,"PRZEWAGA") | D48: =COUNTIFS(Macierz!$B$2:$B$441,"P",Macierz!$K$2:$K$441,"LUKA") | E48: =COUNTIFS(Macierz!$B$2:$B$441,"P",Macierz!$L$2:$L$441,"BLOKER STARTU") | F48: =IFERROR(C48/B48,0)
A49: Q — Przewaga | B49: =COUNTIF(Macierz!$B$2:$B$441,"Q") | C49: =COUNTIFS(Macierz!$B$2:$B$441,"Q",Macierz!$K$2:$K$441,"PARYTET")+COUNTIFS(Macierz!$B$2:$B$441,"Q",Macierz!$K$2:$K$441,"PRZEWAGA") | D49: =COUNTIFS(Macierz!$B$2:$B$441,"Q",Macierz!$K$2:$K$441,"LUKA") | E49: =COUNTIFS(Macierz!$B$2:$B$441,"Q",Macierz!$L$2:$L$441,"BLOKER STARTU") | F49: =IFERROR(C49/B49,0)
A50: X — Infrastruktura jakości | B50: =COUNTIF(Macierz!$B$2:$B$441,"X") | C50: =COUNTIFS(Macierz!$B$2:$B$441,"X",Macierz!$K$2:$K$441,"PARYTET")+COUNTIFS(Macierz!$B$2:$B$441,"X",Macierz!$K$2:$K$441,"PRZEWAGA") | D50: =COUNTIFS(Macierz!$B$2:$B$441,"X",Macierz!$K$2:$K$441,"LUKA") | E50: =COUNTIFS(Macierz!$B$2:$B$441,"X",Macierz!$L$2:$L$441,"BLOKER STARTU") | F50: =IFERROR(C50/B50,0)
A51: Z — Pass adwersaryjny | B51: =COUNTIF(Macierz!$B$2:$B$441,"Z") | C51: =COUNTIFS(Macierz!$B$2:$B$441,"Z",Macierz!$K$2:$K$441,"PARYTET")+COUNTIFS(Macierz!$B$2:$B$441,"Z",Macierz!$K$2:$K$441,"PRZEWAGA") | D51: =COUNTIFS(Macierz!$B$2:$B$441,"Z",Macierz!$K$2:$K$441,"LUKA") | E51: =COUNTIFS(Macierz!$B$2:$B$441,"Z",Macierz!$L$2:$L$441,"BLOKER STARTU") | F51: =IFERROR(C51/B51,0)
A54: UWAGA METODOLOGICZNA
A55: • Procent pokrycia jest metryką OPISOWĄ. Decyzję o starcie podejmuje się wyłącznie na podstawie liczby blokerów.
A56: • Kolumny cPanel/Plesk/DirectAdmin pokazują możliwości silnika — nie to, co hosting faktycznie daje klientowi.
A57: • Werdykt liczony jest wobec kolumny „Rynek PL”, nie wobec sumy możliwości paneli.
A58: • Stan Verris ustalany z kodu (plik:linia), nie z dokumentacji projektu.
A59: • „ATRAPA” = UI bez działającego backendu. „ENDPOINT BEZ UI” = backend gotowy, żaden panel go nie woła.
A60: • Ten plik jest generowany. Zmiany wprowadzaj w audyt/dane/macierz.csv i uruchom audyt/generate.py.

Sheet Macierz
A1: ID | B1: Kat | C1: Funkcja | D1: cPanel | E1: Plesk | F1: DirectAdmin | G1: Rynek PL | H1: Nowa fala | I1: Verris — stan | J1: Dowód (plik:linia) | K1: Werdykt | L1: Krytyczność | M1: Nakład | N1: Uwagi
A2: A-01 | B2: A | C2: Dodanie domeny do konta | D2: TAK | E2: TAK | F2: TAK | G2: TAK | H2: TAK | I2: DZIAŁA | J2: services.controller.ts:539 | K2: PARYTET | L2: — | M2: —
A3: A-02 | B3: A | C3: Usunięcie domeny z konta | D3: TAK | E3: TAK | F3: TAK | G3: TAK | H3: TAK | I3: DZIAŁA | J3: services.controller.ts:548 | K3: PARYTET | L3: — | M3: — | N3: 2026-10-08: usunięcie domeny-poddomeny zdejmuje delegację NS/DS w strefie rodzica (60ff05ba) — D3 t1: z10.d3.hvln.pl dodana (NS+DS w d3.hvln.pl) i usunięta (delegacja znika); sieroty test3/4/5, z18b, z09 usunięte z panelu (DS przez dsrecs0 działa). | 2026-10-08 KOD (495019a5): także usunięcie CAŁEGO konta (retencja, operator, RODO, wycofanie provisioningu), którego domena jest poddomeną domeny innego konta na tym węźle (z18b) — domeny konta czytane przed usunięciem, po nim NS/DS zdejmowane w strefie konta-rodzica (najbliższy żywy przodek, ten sam węzeł), audyt HOSTING_DNS_DELEGATION_REMOVED. Testy D2 + integracja. Zostaje: D3 na t1 (konto z domeną-poddomeną d3.hvln.pl → usunięcie przez operatora → NS/DS znikają z d3.hvln.pl). Poza zakresem nadal: rodzic będący domeną dodatkową innego konta.
A4: A-03 | B4: A | C4: Subdomeny — tworzenie | D4: TAK | E4: TAK | F4: TAK | G4: TAK | H4: TAK | I4: DZIAŁA | J4: services.controller.ts:671 | K4: PARYTET | L4: — | M4: —
A5: A-04 | B5: A | C5: Subdomeny — usuwanie | D5: TAK | E5: TAK | F5: TAK | G5: TAK | H5: TAK | I5: DZIAŁA | J5: services.controller.ts:680 | K5: PARYTET | L5: — | M5: —
A6: A-05 | B6: A | C6: Alias / parkowanie domeny (domain pointer) | D6: TAK | E6: TAK | F6: TAK | G6: TAK | H6: TAK | I6: DZIAŁA | J6: services.controller.ts:562 | K6: PARYTET | L6: — | M6: —
A7: A-06 | B7: A | C7: Zmiana document root domeny | D7: TAK | E7: TAK | F7: TAK | G7: CZĘŚĆ | H7: TAK | I7: DZIAŁA | J7: servers/docroot.ts; servers/directadmin.service.ts getHostingDocroot/setHostingDocroot; GET/POST /services/:id/hosting-docroot; client components/hosting/DocrootPanel.tsx; test servers/docroot.spec.ts; D3 t1 28.09: odczyt zawsze błąd — GET CMD_API_CUSTOM_HTTPD zwraca surową treść .cust_httpd → docroot.ts trescCustomHttpd; retest; D3 t1 29.09 (panel klienta, d3.hvln.pl): „Katalog główny strony” → git-test: po ~1 min / serwuje git-test (v.php 8.1.34, readme Hello Dolly, wp-login 404); „Przywróć public_html” → WordPress znów 200 | K7: PARYTET | L7: NISKA | M7: S | N7: DA to potrafi; brak UI | 2026-09-25 ROZPOZNANIE: DirectAdmin nie ma zmiany document root na poziomie użytkownika — robi się to jako administrator w Custom HTTPD Configurations tokenem |?DOCROOT=/home/<user>/domains/<domena>/public_html/<katalog>| (obejmuje http i https), potem przebudowa konfiguracji serwera WWW. Plan: zadanie węzła z białą listą katalogów wewnątrz public_html (np. public/, web/) — typowo pod Laravel/Symfony. Wymaga ustalenia serwera WWW na węźle (J-01: Apache/LiteSpeed/OpenLiteSpeed mają osobne pliki custom), więc budowa razem z D3 na węźle #1. | 2026-09-25 ŹRÓDŁA OFICJALNE: DirectAdmin „Customizing Apache” — token |?DOCROOT=/nowa/ścieżka| w Custom HTTPD (dla samej domeny: |*if !SUB| … |*endif|), plik data/users/<user>/domains/<domena>.cust_httpd, zastosowanie: task.queue action=rewrite&value=httpd albo da build rewrite_confs. LiteSpeed Enterprise na DA czyta tę konfigurację Apache (dokumentacja LiteSpeed), więc na naszym węźle (webserver=litespeed) mechanizm zadziała. Wcześniejsza notka opierała się na źródle nieoficjalnym. | 2026-09-25 ZROBIONE (D2): strona domeny → PHP → „Katalog główny strony”: podkatalog public_html (do 4 poziomów, bez .., katalog musi istnieć). API GET/POST /services/:id/hosting-docroot (reguła FILES_MANAGE, RateLimit 20/h, dziennik HOSTING_DOCROOT_SET). Zapis przez CMD_API_CUSTOM_HTTPD (oficjalny changelog DA 1.26.0: domain + config) jako admin węzła: blok Verris między znacznikami z |*if !SUB| |?DOCROOT=…| |*endif|, wpisy administratora zostają; gdy DA nie odda bieżącego config — odmowa bez zapisu. Bez zadania węzła (DA sam przepisuje httpd.conf). D3 na węźle: format odpowiedzi GET CMD_API_CUSTOM_HTTPD (pole config), uprawnienie klucza admina do tej komendy, czas przebudowy, działanie pod LSWS i HTTPS.
A8: A-07 | B8: A | C8: Przekierowanie domeny (web forwarding) | D8: TAK | E8: TAK | F8: TAK | G8: TAK | H8: TAK | I8: DZIAŁA | J8: WebToolsTab.tsx:143 | K8: PARYTET | L8: — | M8: — | N8: przez .htaccess
A9: A-08 | B9: A | C9: Rejestracja domeny z panelu | D9: NIE | E9: NIE | F9: NIE | G9: TAK | H9: TAK | I9: DZIAŁA | J9: domains.controller.ts:118 | K9: PARYTET | L9: ŚREDNIA | M9: M | N9: Skorygowane: sekcja jest wpięta w panel (domains/actions.ts:165,181,198), backend kompletny. To brak wpisu w ENV, nie brak funkcji — hosting da się sprzedać na domenie klienta. | 2026-09-27 KOD (4cbc9d4): opłacona rejestracja zapisuje domenę na koncie płacącego także wtedy, gdy ktoś wcześniej dopisał tę nazwę do swojego konta bez weryfikacji (wcześniej zostawała u rezerwującego). Test integracyjny. | 2026-10-04: D3 (sandbox OpenProvidera (api.sandbox.openprovider.nl), panel klienta prod, klient d3 czasowo na portfelu) — rejestracja verris-test-d3-2026.com na 1 rok z kreatora: 70,99 zł z portfela, domena „zarejestrowana, wygasa 4.10.2027”, abonent na kliencie (uchwyt OP). Znalezione: domyślne NS ns1/ns2.verris.pl nie istnieją w DNS → 9eb936d4 (NS węzła/platformy). Prawdziwa rejestracja (produkcyjne konto OP) — PB-05 wg decyzji 27.09. | 2026-10-07 KOD + D3: zmiana serwerów nazw zarejestrowanej domeny (panel → Serwery nazw, OpenProvider PUT /v1/domains/{id} name_servers, walidacja 2–8 hostów, audyt DOMAIN_NAMESERVERS_UPDATED) — d91ce97. verris-test-d3-2026.com z 04.10 miała ns1/ns2.verris.pl → ustawione ns3/ns4.verris.pl, rejestrator przyjął.
A10: A-09 | B10: A | C10: Transfer domeny (kod authinfo) | D10: NIE | E10: NIE | F10: NIE | G10: TAK | H10: TAK | I10: CZĘŚCIOWE | J10: POST /domains/:id/registrar/authcode (A-09, tylko właściciel konta, 5/h, audyt DOMAIN_AUTHCODE_REVEALED bez kodu) → OpenProvider GET /v1/domains/{id}/authcode; panel: Domeny → domena → „Transfer i abonent” → Pokaż kod; transfer PRZYCHODZĄCY: formularz z danymi abonenta i oświadczeniem; test domains/abonent-domeny.spec.ts | K10: CZĘŚCIOWY | L10: WYSOKA | M10: M | N10: j.w. | 2026-09-23: kod transferu wychodzącego z panelu. ZNALEZISKO: formularz transferu przychodzącego nie wysyłał oświadczenia o odstąpieniu, a API go wymaga — każdy transfer kończył się błędem 400, bez komunikatu (akcja formularza). Przepisany na formularz z komunikatem błędu. FLAGA do konfiguracji OpenProvider (A-11). | 2026-09-27 KOD: klient zlecał transfer bez zobaczenia kwoty (obciążenie portfela). Nowy POST /domains/registrar/quote-transfer (ta sama ścieżka ceny co transfer()), formularz pokazuje koszt brutto i blokuje „Zleć transfer” bez ceny; pola z etykietami, historia zleceń po polsku (a186d54). D3 przy teście z węzłem. | 2026-09-27 KOD (4cbc9d4): transfer zostawał na zawsze „wysłany do rejestru” — domena nie pojawiała się na koncie po udanym przeniesieniu. Nowe zadanie co godzinę (domains:transfer-sync): stan u rejestratora ACT → domena na koncie płacącego z datą wygaśnięcia, FAI/DEL → zwrot na portfel. Kody stanów OpenProvidera do potwierdzenia przy pierwszym prawdziwym transferze (D3 z węzłem). | 2026-09-27 PRODUKCJA: cena transferu przed zleceniem działa (hvln.pl 0,99 zł brutto, przycisk zablokowany bez ceny, etykiety pól). Poprawka tekstu: transfer .pl nie przedłuża ważności (NASK) — usunięte pole lat i obietnica „przedłużenia o rok” dla .pl. | 2026-10-04: D3 (sandbox OpenProvidera (api.sandbox.openprovider.nl), panel klienta prod, klient d3 czasowo na portfelu) — kod transferu (AuthInfo) z rejestratora: 12 znaków, wyświetlenie w dzienniku; odblokowanie przed transferem działa (A-15). Sam transfer przychodzący — sandbox OP go nie obsługuje; zostaje do produkcyjnego konta OP. | 2026-10-04 DECYZJA WŁAŚCICIELA: prawdziwy transfer przychodzący w PB-05 (produkcyjne konto OP, grudzień). | 2026-10-07 KOD: webhook OpenProvidera (podpis HMAC + klucz, Caddy tylko adresy OP): incomingTransfer* domyka transfer od razu, outgoingTransferCompleted/deletionCompleted = domena odeszła (bez odnowień i przypomnień); codzienne sprawdzenie stanu jako zabezpieczenie — 20c5196. Transfer wychodzący wcześniej nieobsługiwany. Webhook do włączenia: klucze (prod-ustaw-klucze.sh openprovider) + formularz OP. | 2026-10-07 PRODUKCJA: webhook zapisany w panelu OP (sandbox); test OP dotarł do API — 2× REGISTRAR_WEBHOOK w dzienniku (13:16 UTC). Sandbox OP wysyła z 34.91.59.39 (brak w dokumentacji OP, wykryte tcpdumpem) — dopisany do Caddy (503c1c3); odrzucenia logowane z powodem (fe283d0).
A11: A-10 | B11: A | C11: Odnowienie domeny przez klienta | D11: NIE | E11: NIE | F11: NIE | G11: TAK | H11: TAK | I11: DZIAŁA | J11: panel: Domeny → domena → „Odnowienie domeny” (domain-renew-box.tsx: okres → cena z nowego POST domains/:id/registrar/renew-quote → potwierdzenie → POST domains/:id/registrar/renew, obciążenie portfela, zwrot przy błędzie rejestratora); liczba lat walidowana 1–10 (wcześniej body bez walidacji) | K11: PARYTET | L11: ŚREDNIA | M11: S | N11: Skorygowane: brak wywołania potwierdzony, ale obejście istnieje (panel rejestratora). Nie spełnia żadnego z czterech warunków blokera. | 2026-09-23: UI zrobione. Działa po włączeniu rejestratora (A-08/A-11 FLAGA — REGISTRAR_PROVIDER); do tego czasu pole pokazuje się tylko domenom z datą ważności z rejestratora. | 2026-10-04: D3 (sandbox OpenProvidera (api.sandbox.openprovider.nl), panel klienta prod, klient d3 czasowo na portfelu) — „Odnów za 70,99” → „Domena odnowiona”, portfel −70,99 (240,11 po rejestracji i odnowieniu). Błąd: data ważności w panelu została 4.10.2027 (odpowiedź renew bez expiration_date) → 9eb936d4 czyta datę z domeny u rejestratora; retest po wdrożeniu. | 2026-10-04 po c240269: drugie odnowienie w sandboxie — „Ważna do 4.10.2029” (data z rejestru, domainInfo), portfel −70,99 jednorazowo (169,12). Opis w historii „(1 lata/lat)” → „(1 rok)” poprawiony.
A12: A-11 | B12: A | C12: Wyszukiwarka wolnych domen | D12: NIE | E12: NIE | F12: NIE | G12: TAK | H12: TAK | I12: DZIAŁA | J12: domains.controller.ts:54 | K12: PARYTET | L12: WYSOKA | M12: S | N12: DECYZJA WŁAŚCICIELA 2026-09-23: konfiguracja OpenProvider (REGISTRAR_PROVIDER + dane API w .env.prod, wpisuje właściciel) razem z zakupem węzła w sprincie 18; do tego czasu wyszukiwarka za flagą. | 2026-09-25: preflight GO-LIVE blokuje start bez REGISTRAR_PROVIDER (strona oferuje rejestrację domen). Wyszukiwarka na verris.pl prowadzi do /dashboard/domains/buy?domain=… i panel wpisuje nazwę w wyszukiwarkę (wcześniej nazwa przepadała). /domeny: „bez blokad transferu” → blokadę włączasz i zdejmujesz sam (A-15). | 2026-09-27 PRODUKCJA po b0a556f: wyszukiwarka działa — „hvln-test-verris” → 32 wolne warianty z ceną rejestracji i odnowienia (brutto). Przyczyna „wszystko zajęte”: OpenProvider zwraca wyniki w innej kolejności niż w zapytaniu — dopasowanie po nazwie domeny, zapytania po 15 końcówek. Zostaje do pełnego testu z węzłem (decyzja właściciela). | 2026-10-04: D3 (sandbox OpenProvidera (api.sandbox.openprovider.nl), panel klienta prod, klient d3 czasowo na portfelu) — wyszukiwarka: 26 z 32 końcówek z cenami brutto. Po drodze: paczka 15 TLD „wszystko albo nic” gubiła .pl/.com, gdy jedna końcówka wisiała (.online/.shop >40 s w sandboxie) → 36b8bca/9199355/99e38ec (limit 6 s, pojedynczo po błędzie paczki, budżet panelu 40 s); końcówki bez odpowiedzi „Nie sprawdzono” zamiast „Zajęta” → 9eb936d4.
A13: A-12 | B13: A | C13: Cennik rejestracji na 1–10 lat | D13: NIE | E13: NIE | F13: NIE | G13: TAK | H13: TAK | I13: DZIAŁA | J13: POST domains/registrar/quote-periods (domain-registrar.service.ts quotePeriods — ceny brutto dla 1, 2, 3, 5 i 10 lat + cena odnowienia/rok) → kreator zakupu: krok „Okres” z ceną każdego wariantu (domain-purchase-wizard.tsx YEAR_OPTIONS) | K13: PARYTET | L13: ŚREDNIA | M13: S | N13: 2026-09-23 PORZĄDKI: funkcja była zrobiona, wpis „LUKA” był nieaktualny. Działa po włączeniu rejestratora (A-11 FLAGA — REGISTRAR_PROVIDER), tak jak A-10. | 2026-09-27 PRODUKCJA: okresy dla hvln-test-verris.pl — 1 rok 24,99 zł, 2 lata 91,99, 3 lata 192,99, 5 lat 360,99, 10 lat 781,99, odnowienie 83,99 zł/rok (ceny OpenProvider × marża, brutto). Zostaje do pełnego testu z węzłem. | 2026-10-04: D3 (sandbox OpenProvidera (api.sandbox.openprovider.nl), panel klienta prod, klient d3 czasowo na portfelu) — okres 1/2/3/5/10 lat: 70,99 / 140,99 / 211,99 / 352,99 / 705,99 zł brutto dla .com, odnowienie 70,99 zł/rok widoczne przed zakupem; podsumowanie netto 57,72 + VAT 13,27.
A14: A-13 | B14: A | C14: Zmiana danych abonenta domeny | D14: NIE | E14: NIE | F14: NIE | G14: TAK | H14: TAK | I14: DZIAŁA | J14: GET/PUT /domains/:id/registrar/registrant (tylko właściciel konta) → OpenProvider /v1/customers/{handle}; rejestracja i transfer zakładają uchwyt klienta (POST /v1/customers) przed obciążeniem portfela; panel: kreator zakupu, zamówienie hostingu z domeną, transfer, strona domeny; test domains/abonent-domeny.spec.ts | K14: PARYTET | L14: WYSOKA | M14: M | N14: wymóg operatorski przy własnej rejestracji | DECYZJA WŁAŚCICIELA 2026-09-23: abonentem jest KLIENT. ZNALEZISKO: kod rejestrował każdą domenę na uchwyt operatora (OPENPROVIDER_OWNER_HANDLE jako owner) — formalnie domeny należałyby do Verris, sprzecznie z projektem Regulaminu §12 ust. 4 („rejestrowana na dane Klienta”). Nic nie zostało zarejestrowane (rejestrator za flagą), więc zmiana bez migracji. Handle operatora zostaje jako admin/tech/billing. Imię, nazwisko i firmę zmienia tylko cesja (rejestrator nie modyfikuje nazwy uchwytu) — panel odmawia z wyjaśnieniem; adres, telefon, e-mail, NIP — z panelu. PRZY OKAZJI: /v1beta → /v1 (OpenProvider wyłącza v1beta 2027-06-30). D3 przy pierwszej domenie po konfiguracji OpenProvider. | 2026-10-04: D3 (sandbox OpenProvidera (api.sandbox.openprovider.nl), panel klienta prod, klient d3 czasowo na portfelu) — „Dane abonenta”: odczyt z rejestratora, zmiana miasta/kodu (Warszawa 00-001 → Kraków 30-001) „zapisane u rejestratora”, po przeładowaniu odczyt z OP pokazuje nowe dane; imię/nazwisko/firma tylko przez cesję (zgłoszenie).
A15: A-14 | B15: A | C15: Ukrycie danych WHOIS / domain privacy | D15: NIE | E15: NIE | F15: NIE | G15: b.d. | H15: TAK | I15: DZIAŁA | J15: domain-registrar.service.ts setWhoisPrivacy (OpenProvider PUT /v1/domains/{id} is_private_whois_enabled); Domain.whoisPrivacy; zamówienie WHOIS_PRIVACY; ustawienie domain.whoisPrivacyYearlyPrice (puste = ukryte); migracja 20261005160000_ukrycie_whois | K15: PARYTET | L15: NISKA | M15: S | N15: DECYZJA WŁAŚCICIELA 2026-09-24: po starcie — u OpenProvider ukrycie WHOIS to usługa płatna per domena, a dla osób fizycznych z .pl rejestr i tak nie publikuje danych; wracamy przy sprzedaży domen, gdy znane będą koszty. | 2026-10-05 KOD (decyzja właściciela: budujemy teraz; członkostwo OP Basic „S” — usługa płatna): dodatek płatny, cena brutto za rok w Ustawieniach platformy (puste = niedostępne), opłata za rozpoczęte lata do wygaśnięcia + dopłata przy odnowieniu, odmowa rejestru → zwrot (bc35db54). Zostaje: cena od właściciela, test w sandboxie OP (model opłat, kod błędu .pl). | 2026-10-05 KOREKTA STANU: kod jest (c2bd935), wpis zostawał „BRAK/LUKA” — teraz FLAGA (cena pusta = funkcja ukryta) · CZĘŚCIOWY do ceny i testu w sandboxie OP. | 2026-10-06 D3 SANDBOX: włączenie ukrycia dla verris-test-d3-2026.com (29,97 K = 3 lata do końca ważności) — OpenProvider „Wpp contract is not signed”; zwrot zadziałał; komunikat klienta poprawiony (0827480). Zostaje: akceptacja umowy WPP w panelu OpenProvidera (właściciel), ponowny test. | 2026-10-07 D3 SANDBOX po podpisaniu umowy WPP (sandbox + produkcja): włączenie dla verris-test-d3-2026.com — 29,97 K z portfela, „Dane w WHOIS ukryte”; wyłączenie bez opłaty działa. Zamknięte 2026-10-07. Do decyzji: ponowne włączenie w tym samym okresie pobiera opłatę jeszcze raz. | 2026-10-07 DECYZJA WŁAŚCICIELA: ukrycie danych bezpłatne (WPP w członkostwie OpenProvidera), cena dalej ustawiana w adminie: 0 = bezpłatnie, puste = niedostępne (3bc7107). D3: cena 0 w adminie, włączenie na verris-test-d3-2026.com — audyt priceAmount 0.00, bez zamówienia i bez obciążenia portfela. Kwestia ponownej opłaty w tym samym okresie nieaktualna.
A16: A-15 | B16: A | C16: Blokada transferu domeny (transfer lock) | D16: NIE | E16: NIE | F16: NIE | G16: b.d. | H16: TAK | I16: DZIAŁA | J16: POST /domains/:id/registrar/lock → OpenProvider PUT /v1/domains/{id} {is_locked}; stan w Domain.transferLock + audyt DOMAIN_TRANSFER_LOCKED/UNLOCKED; panel: strona domeny „Transfer i abonent”; test domains/abonent-domeny.spec.ts | K16: PARYTET | L16: ŚREDNIA | M16: S | N16: 2026-09-23: przełącznik blokady w panelu. FLAGA do konfiguracji OpenProvider (A-11). | 2026-10-04: D3 (sandbox OpenProvidera (api.sandbox.openprovider.nl), panel klienta prod, klient d3 czasowo na portfelu) — blokada transferu: domyślnie włączona, „Odblokuj” → wyłączona (po przeładowaniu z rejestratora nadal wyłączona), „Zablokuj” → włączona.
A17: A-16 | B17: A | C17: Weryfikacja własności domeny | D17: NIE | E17: NIE | F17: NIE | G17: b.d. | H17: b.d. | I17: DZIAŁA | J17: domains.service.ts verifyDomain — ACTIVE tylko po rekordzie TXT _verris-challenge.<domena> = verris-verify=<HMAC(id,właściciel)>; create zwalnia cudzą niezweryfikowaną rezerwację po 7 dniach; klient: domains/[id] — instrukcja TXT z kopiowaniem; testy D2 domains.service.spec.ts | K17: PARYTET | L17: WYSOKA | M17: M | N17: OBALONE w passie adwersaryjnym: to checklist konfiguracji, nie dowód własności. Brak wyzwania TXT i tokenu — dowolny użytkownik może dodać cudzą domenę i doprowadzić ją do statusu ACTIVE. | 2026-09-23: domena przechodzi w ACTIVE dopiero po opublikowaniu rekordu TXT (wartość różna dla każdego właściciela, liczona HMAC — bez migracji). Checklist A/NS/TLS zostaje jako asystent konfiguracji, nie dowód. Anty-squatting: niezweryfikowana cudza rezerwacja po 7 dniach nie blokuje nazwy. Domeny kupione przez rejestratora są ACTIVE z zakupu. D3 na pierwszej domenie klienta.
A18: A-17 | B18: A | C18: Rejestracja konta klienta (self-service) | D18: NIE | E18: NIE | F18: NIE | G18: TAK | H18: TAK | I18: DZIAŁA | J18: auth.controller.ts:67 | K18: PARYTET | L18: — | M18: — | N18: captcha + weryfikacja e-mail
A19: A-18 | B19: A | C19: Logowanie hasłem | D19: TAK | E19: TAK | F19: TAK | G19: TAK | H19: TAK | I19: DZIAŁA | J19: auth.controller.ts:77 | K19: PARYTET | L19: — | M19: —
A20: A-19 | B20: A | C20: Zamówienie usługi z panelu | D20: NIE | E20: NIE | F20: NIE | G20: TAK | H20: TAK | I20: DZIAŁA | J20: subscriptions.controller.ts:97 | K20: PARYTET | L20: — | M20: —
A21: A-20 | B21: A | C21: Okres próbny / trial | D21: NIE | E21: NIE | F21: NIE | G21: CZĘŚĆ | H21: TAK | I21: DZIAŁA | J21: subscriptions.controller.ts:53 | K21: PARYTET | L21: — | M21: — | N21: 3 z 5 hostingów PL ma trial lub money-back | 2026-10-06: trial omijał blokadę PB-28 (rozliczani poza Verris) — 645a250 (test trial.billing-outside.spec.ts).
A22: A-21 | B22: A | C22: Anulowanie usługi przez klienta | D22: NIE | E22: NIE | F22: NIE | G22: TAK | H22: TAK | I22: DZIAŁA | J22: subscriptions.controller.ts:103; D3 t1 (d3.hvln.pl) 29.09 00:38: rezygnacja „od razu” z mailtest-verris.pl w panelu klienta → status Anulowana, konto DA zawieszone | K22: PARYTET | L22: — | M22: —
A23: A-22 | B23: A | C23: Zmiana planu (upgrade/downgrade) z proratą | D23: NIE | E23: NIE | F23: NIE | G23: CZĘŚĆ | H23: TAK | I23: DZIAŁA | J23: subscriptions.controller.ts:146,161 | K23: PRZEWAGA | L23: — | M23: — | N23: prorata cross-interval MONTH↔YEAR; test D1 | 2026-09-27 ZNALEZISKO (naprawione c0991f1): zmiana okresu rozliczeniowego liczyła koszt jak resztę starego okresu, a zaczynała nowy pełny okres — miesiąc→rok w połowie miesiąca = rok gratis + ~6 zł zwrotu; rok→miesiąc = dopłata ~136 zł zamiast zwrotu. Teraz pełna cena nowego okresu minus niewykorzystana część starego (Regulamin: zmiana okresu rozpoczyna nowy okres). Równoległe zmiany planu zajmują usługę warunkowo (drugie żądanie 409). Test integracyjny zmiana-planu.int-spec.ts. DO SPRAWDZENIA NA PRODUKCJI: czy ktoś zmieniał okres z portfela (zdarzenia PLAN_CHANGED z intervalChange=true). | 2026-09-27 PRODUKCJA: sprawdzone w dzienniku — 0 zmian okresu rozliczeniowego (PLAN_CHANGED z intervalChange=true), błąd nie został wykorzystany; bez korekt wstecz.
A24: A-23 | B24: A | C24: Dane dostępowe usługi (IP/FTP/NS/limity) | D24: TAK | E24: TAK | F24: TAK | G24: TAK | H24: TAK | I24: DZIAŁA | J24: services.controller.ts:355 | K24: PARYTET | L24: — | M24: —
A25: A-24 | B25: A | C25: Zakładanie konta klienta przez operatora | D25: TAK | E25: TAK | F25: TAK | G25: TAK | H25: TAK | I25: DZIAŁA | J25: POST /admin/users (users.admin.controller.ts createCustomer, CUSTOMERS_MANAGE) → UsersAdminService.createCustomerByOperator; admin: Klienci → „Nowy klient” (create-customer-button.tsx); testy D2 users.admin.create-customer.spec.ts + users.admin.controller.spec.ts | K25: PARYTET | L25: WYSOKA | M25: M | N25: Skorygowane: konta powstają też przez rejestrację (auth.service.ts:132) — operator może zarejestrować za klienta i wejść przez impersonację (users.admin.controller.ts:248). Pierwsze konto da się sprzedać. | 2026-09-23: operator zakłada konto bez znajomości hasła — klient dostaje link „ustaw hasło” (72 h, token PASSWORD_RESET), ustawienie hasła potwierdza e-mail. Zgód nie składamy w imieniu klienta: regulamin akceptuje sam przy pierwszym logowaniu. Audyt ADMIN_CUSTOMER_CREATED_BY_OPERATOR. D3 przy pierwszym koncie z telefonu.
A26: A-25 | B26: A | C26: Ręczne zawieszenie usługi przez operatora | D26: TAK | E26: TAK | F26: TAK | G26: TAK | H26: TAK | I26: DZIAŁA | J26: 2026-09-23 D1: admin-panel subscriptions/[id]/suspend-form.tsx + suspend-actions.ts → POST /admin/subscriptions/:id/suspend (powód, notatka, potwierdzenie); D3 t1 (d3.hvln.pl) 29.09 01:1x: zawieszenie z panelu admina (Decyzja operatora + notatka) → strona pokazuje stronę zawieszenia DA, sesja DA klienta wylogowana. Uwaga: strona zawieszenia to domyślna, angielska strona DA (bez marki Verris) | K26: PARYTET | L26: — | M26: S | N26: Skorygowane: endpoint działa i jest osiągalny (curl + DirectAdmin), auto-suspend za brak płatności działa. Brakuje UI, nie możliwości zatrzymania szkody. | UI zrobione. OTWARTE do D3 (PB-21, serwer testowy): zawieszenie konta w DirectAdminie na żywym węźle.
A27: A-26 | B27: A | C27: Ręczne odwieszenie usługi przez operatora | D27: TAK | E27: TAK | F27: TAK | G27: TAK | H27: TAK | I27: DZIAŁA | J27: 2026-09-23 D1: ten sam formularz — odwieszenie z opcją obciążenia za odnowienie (chargeRenewal); D3 t1 (d3.hvln.pl) 29.09: odwieszenie bez obciążenia → WordPress wraca po kilku sekundach | K27: PARYTET | L27: — | M27: S | N27: Skorygowane: jak A-25, endpoint subscriptions.admin.controller.ts:210 działa z chargeRenewal. | UI zrobione. OTWARTE do D3 (PB-21): odwieszenie konta w DA na żywym węźle.
A28: A-27 | B28: A | C28: Pakiety / plany zasobów po stronie operatora | D28: TAK | E28: TAK | F28: TAK | G28: TAK | H28: TAK | I28: DZIAŁA | J28: plans.admin.controller.ts:45 | K28: PARYTET | L28: — | M28: —
A29: A-28 | B29: A | C29: Impersonacja klienta przez operatora | D29: TAK | E29: TAK | F29: TAK | G29: b.d. | H29: b.d. | I29: DZIAŁA | J29: users.admin.controller.ts:248; common/auth/przekazanie-sesji.ts | K29: PARYTET | L29: — | M29: — | N29: z banerem u klienta | 2026-09-25 (impersonacja „jako klient”): (1) /impersonate przyjmował dowolny token — link ze zwykłym tokenem napastnika logował ofiarę na jego konto (login CSRF); teraz tylko token z claimem impersonatedBy (podpis sprawdza API). (2) returnTo „//host” przechodziło jako ścieżka → przekierowanie na obcą domenę; teraz tylko ścieżki panelu. (3) token impersonacji nie niósł wersji sesji, więc u klientów po „wyloguj wszędzie”/resecie hasła impersonacja od razu kończyła się 401; teraz tv = tokenVersion klienta. (4) działania w impersonacji trafiają do dziennika z impersonatedBy (G-18). Test apps/client-panel/src/app/impersonate/route.spec.ts. | 2026-09-25 (przegląd adwersaryjny paneli): token impersonacji nie idzie już w URL — API zwraca jednorazowy kod (60 s, jednorazowy), panel klienta wymienia go serwer-serwer na POST /auth/handoff; zły kod nie wylogowuje klienta; returnTo tylko ta sama origin (zamknięty open redirect „/\t/evil”). Dowód: common/auth/przekazanie-sesji.ts + spec, client-panel impersonate/route.spec.ts. | 2026-10-10: przycisk „Zaloguj jako klient” w panelu obsługi tylko z CUSTOMERS_VIEW + CUSTOMERS_IMPERSONATE (staff-panel lib/staff-access.ts:31-35, test zaloguj-jako-klient.spec.tsx); passkey klienta zablokowany w sesji impersonacji (33d775dc, audyt bezpieczeństwa 09.10 A07).
A30: B-01 | B30: B | C30: Zmiana wersji PHP dla całego konta | D30: TAK | E30: TAK | F30: TAK | G30: TAK | H30: TAK | I30: DZIAŁA | J30: services.controller.ts:125; D3 t1 28.09: FAIL — selektor bez alt-php (profil nie instalował els-php-release/alt-phpXX na CL10), panel pokazywał wersję mimo błędu → profil + PHP_APPLY cofa wersję (int: php-odrzucona-zmiana.int-spec.ts); retest po profilu; D3 t1 (d3.hvln.pl) 28.09 23:31: PHP 8.2 dla konta z panelu → strona zwraca 8.2.33 na LiteSpeed (PHP_APPLY zakończone); odrzucona zmiana cofa wersję (int) | K30: PARYTET | L30: — | M30: S | N30: KOREKTA: pozycja miała stan DZIAŁA na podstawie kodu i kolejki PHP_APPLY. Odkryte 2026-08-21 przy przeglądzie Dockerfile.api: loadery skryptów w API czytają plik z dysku i rzucają wyjątkiem, gdy go nie ma, a obraz produkcyjny kopiował tylko 7 z 10 potrzebnych skryptów. Endpoint /agent/tasks/php-apply/script zwracał 500, więc agent nie miał czego uruchomić — zadanie PHP_APPLY nie mogło się wykonać na produkcji ani razu. Naprawione (COPY + test apps/api/src/test/dockerfile-scripts.spec.ts), ale do czasu potwierdzenia na produkcji stan to CZĘŚCIOWE: kod i testy były zielone przez cały czas, więc D1 i D2 nic tu nie dowodzą — potrzebny D3. | 2026-08-21 21:57: przyczyna wdrożeniowa USUNIĘTA — node-php-apply.sh jest już w obrazie (potwierdzone na serwerze, X-12 D3). Pozycja zostaje CZĘŚCIOWE, bo jej własny dowód wymaga wykonania zadania PHP_APPLY na żywym węźle, a węzła jeszcze nie ma. Do przejścia z części B checklisty D3. | WYCENA 2026-09-19: krytycznosc i naklad uzupelnione przy wznowieniu. Pozycje przepisane 2026-08-28 w ramach X-49 zostaly bez wyceny, przez co nie liczyly sie do budzetu godzin i nie stały w zadnym sprincie. Podstawa wyceny: Zmiana wersji PHP dla calego konta — per domena juz dziala (B-02, S), to ten sam mechanizm o poziom wyzej. | 2026-09-22: przeniesione do sprintu 18 — kod i obraz sa gotowe, zostal wylacznie dowod D3 (PHP_APPLY na zywym wezle).
A31: B-02 | B31: B | C31: Zmiana wersji PHP per domena | D31: TAK | E31: TAK | F31: TAK | G31: TAK | H31: TAK | I31: DZIAŁA | J31: services.controller.ts — GET/POST /services/:id/hosting-domain-php; directadmin.service.ts:2058; D3 t1 28.09: slot DA php1_select wskazywał nieistniejące php2_release i wyłączał selektor CL → teraz alt-php w bloku Verris .htaccess domeny: htaccess.service.ts phpDomeny/phpDomenyStatus, node-htaccess.sh „zachowaj”; retest po alt-php; 29.09 profil: [OK] handlery alt-php 83/82/81/80/74 w LiteSpeed — retest PHP domeny do zrobienia; D3 t1 29.09 rano: PHP 8.1 per domena z panelu cofany przez sondę node-htaccess (LiteSpeed potrzebuje chwili po zmianie .htaccess; ręcznie 7.4/8.1/8.2 działają) — poprawka 3273ffa (6 prób, https) czeka na push; D3 t1 (d3.hvln.pl) 29.09 po wdrożeniu (panel klienta): PHP 8.1 dla domeny z panelu → „używana teraz”, strona odpowiada PHP/8.1.34; powrót „Jak konto” działa (3273ffa) | K31: PARYTET | L31: — | M31: S | N31: Decyzja produktowa: ustawienie per domena wygrywa nad ustawieniem konta, a UI musi to pokazywać — php-client.tsx wypisuje domeny z własną wersją PHP przy karcie konta. Zamknięte 2026-08-21 (commit 6f2833d). Strażnik: apps/api/src/test/ui-routes-coverage.spec.ts porównuje wszystkie wywołania apiFetch z panelu ze wszystkimi trasami API — nawrót tej klasy błędu zapala test.
A32: B-03 | B32: B | C32: Zmiana wersji PHP per katalog | D32: TAK | E32: TAK | F32: TAK | G32: CZĘŚĆ | H32: NIE | I32: DZIAŁA | J32: ops/scripts/node-htaccess.sh (HT_DIR, HT_PHP); htaccess.service.ts phpKatalogu; services.controller.ts :id/hosting-htaccess/php-dir; client-panel PhpKatalogPanel (widok strony → PHP i serwer); test htaccess.service.spec.ts; D3 t1 29.09 (panel klienta, d3.hvln.pl): „PHP w podkatalogu” git-test → PHP 8.1: /git-test/v.php zwraca 8.1.34, reszta strony dalej 8.2.33 | K32: PARYTET | L32: NISKA | M32: M | N32: | ZROBIONE W KODZIE 2026-09-25: wersja PHP podkatalogu wg dokumentacji LiteSpeed (DirectAdmin → PHP): <IfModule LiteSpeed> AddHandler application/x-httpd-alt-phpXY .php w bloku Verris pliku .htaccess tego katalogu (CloudLinux alt-php). Katalog sprawdzany jako klient po rozwinięciu dowiązań (dowiązanie poza stronę → odmowa), wersja musi być zainstalowana (/opt/alt/phpXY), po zapisie kontrola katalogu i powrót poprzedniego pliku przy 5xx. Sprawdzone lokalnie (zapis, odczyt, wyczyszczenie, 5 odmów). D3 w wezel.csv.
A33: B-04 | B33: B | C33: Włączanie/wyłączanie rozszerzeń PHP | D33: TAK | E33: TAK | F33: TAK | G33: CZĘŚĆ | H33: TAK | I33: DZIAŁA | J33: ops/scripts/node-php-info.sh (selektor); ops/scripts/node-php-apply.sh (PHP_EXT_ENABLE/DISABLE); subscriptions/php.service.ts setExtensionsForSubscription; POST /services/:id/hosting-php/extensions; client PhpInfoPanel.tsx; testy php.service.spec.ts, php-info.service.spec.ts; D3 t1 29.09 (panel klienta, d3.hvln.pl): włączenie opcache i redis dla PHP 8.2 z panelu → ponowny odczyt: 59 rozszerzeń, opcache.enable = włączone, redis załadowany | K33: PARYTET | L33: ŚREDNIA | M33: M | N33: 2026-09-24: podgląd włączonych rozszerzeń jest (B-06). Przełączanie z panelu wymaga selektora PHP na węźle (CloudLinux/alt-php) — do decyzji przy konfiguracji węzła w sprincie 21; do tego czasu włączamy na prośbę w zgłoszeniu (tekst w panelu). | 2026-09-25 ZROBIONE (D2) wg oficjalnej dokumentacji CloudLinux (selectorctl): odczyt PHP_INFO dokłada --user-current i --list-user-extensions --all (+ włączone, - wyłączone, ~ wbudowane); panel strony → PHP → „Aktualna konfiguracja PHP” ma przełączniki rozszerzeń (wbudowane zablokowane) i „Zastosuj zmiany” → zadanie PHP_APPLY z --enable/--disable-user-extensions dla bieżącej wersji. Przy okazji PHP_APPLY poprawione na oficjalne --set-user-current (było --set-current-version, którego nie ma w dokumentacji) i usunięty „zapasowy” wpis do task.queue DA, który zgłaszał sukces bez zmiany — bez selectorctl zadanie kończy się czytelnym błędem. D3 na węźle: selectorctl dostępny, konto na alt-php (nie native), przełączenie intl/imagick widoczne w ponownym odczycie.
A34: B-05 | B34: B | C34: Edycja dyrektyw php.ini z panelu | D34: TAK | E34: TAK | F34: TAK | G34: TAK | H34: TAK | I34: DZIAŁA | J34: servers/php-ini.ts (lista dozwolonych dyrektyw, zakresy), directadmin.service.ts getHostingPhpIni/setHostingPhpIni (blok panelu w .user.ini domeny), services.controller.ts :id/hosting-php-ini, client-panel components/hosting/PhpIniForm.tsx (widok strony → PHP); testy php-ini.spec.ts + directadmin.domeny.spec.ts; D3 t1 (d3.hvln.pl) 29.09 po wdrożeniu (panel klienta): memory_limit 256M z panelu → blok Verris w .user.ini domeny; D3 t1 29.09: memory_limit 256M z .user.ini nie działał na LiteSpeed (LSAPI bez LSPHP_ENABLE_USER_INI); php_value w .htaccess działa (test 300M) — 98e6f24 zapisuje oba | K34: PARYTET | L34: — | M34: M | N34: 2026-09-24: KOD (D2) — ustawienia PHP per domena z panelu: memory_limit, upload_max_filesize, post_max_size, max_execution_time, max_input_time, max_input_vars, display_errors, date.timezone. Zapis w bloku zarządzanym .user.ini; wpisy klienta poza blokiem zostają. OTWARTE do D3 (sprint 18, węzeł): czy PHP (FPM/LSAPI) czyta .user.ini z docroot i po ilu minutach. | 4 z 5 hostingów PL to ma | 2026-09-24 SKALA DOWODU (decyzja PM): funkcja bez pieniędzy, danych klienta i dostępu — D2 (test w CI) wystarcza do „zrobione”, więc werdykt PARYTET. Stan zostaje CZĘŚCIOWE do testu na węźle (audyt/dane/wezel.csv). | 2026-09-29 D3 t1: memory_limit 512M ustawiony w panelu działa na LiteSpeed (odczyt przez serwer WWW) — blok php_value w .htaccess (98e6f24).
A35: B-06 | B35: B | C35: Podgląd aktualnej konfiguracji PHP (phpinfo) | D35: TAK | E35: TAK | F35: TAK | G35: CZĘŚĆ | H35: TAK | I35: DZIAŁA | J35: ops/scripts/node-php-info.sh; subscriptions/php-info.service.ts; PhpInfoPanel.tsx (strona → PHP i serwer); D3 t1 28.09: FAIL — odczyt przez 127.0.0.1 trafiał w stronę domyślną (vhosty DA na IP konta) → ip= z user.conf; retest; D3 t1 (d3.hvln.pl) 28.09 23:39: podgląd konfiguracji PHP zakończony po poprawce ip= z user.conf | K35: PARYTET | L35: — | M35: S | N35: 2026-09-24: KOD (D2) + skrypt sprawdzony lokalnie na serwerze PHP — konfiguracja tak, jak widzi ją serwer WWW strony (nie PHP z konsoli): wersja, SAPI, 22 dyrektywy i lista rozszerzeń. Plik o losowej nazwie w katalogu strony, odczyt przez 127.0.0.1 z nagłówkiem Host (HTTP, potem HTTPS), usuwany zawsze — także przy błędzie. Bez pełnego phpinfo() (zmienne środowiska, ścieżki). OTWARTE do D3 (sprint 21). | 2026-09-24 SKALA DOWODU (decyzja PM): funkcja bez pieniędzy, danych klienta i dostępu — D2 (test w CI) wystarcza do „zrobione”, więc werdykt PARYTET. Stan zostaje CZĘŚCIOWE do testu na węźle (audyt/dane/wezel.csv).
A36: B-07 | B36: B | C36: Wybór handlera PHP (LSAPI/FPM/CGI) | D36: TAK | E36: TAK | F36: TAK | G36: NIE | H36: NIE | I36: BRAK | J36: — | K36: POZA ZAKRESEM | L36: NISKA | M36: — | N36: decyzja operatorska, nie klienta
A37: B-08 | B37: B | C37: Aplikacje Node.js | D37: TAK | E37: TAK | F37: CZĘŚĆ | G37: NIE | H37: TAK | I37: DZIAŁA | J37: ops/scripts/node-app-selector.sh (zadanie APP_SELECTOR); subscriptions/app-selector.service.ts; services.controller.ts :id/hosting-apps; client-panel components/hosting/AplikacjeSelektorPanel.tsx (zakładka Aplikacje); node-hosting-profile.sh (alt-nodejs/alt-python + selektory włączone); testy test/aplikacje-selektor.spec.ts, app-selector.service.spec.ts | K37: PARYTET | L37: NISKA | M37: L | N37: żaden z 5 hostingów PL tego nie ma | 2026-09-25 KOD (D2): CloudLinux Selector wg oficjalnej dokumentacji (docs.cloudlinux.com → Command-line tools → Node.js/Python Selector; instalacja DirectAdmin: alt-nodejs/alt-python, lvemanager lve-utils alt-python-virtualenv alt-mod-passenger, --selector-status enabled). Zakładka Aplikacje → „Aplikacje Node.js i Python”: utwórz (język, wersja z serwera, domena + ścieżka, katalog poza public_html, plik startowy, obiekt WSGI, zmienne środowiskowe), edytuj (wersja, plik startowy, zmienne), uruchom/zatrzymaj/restart, zależności (npm install / pip -r requirements.txt), usuń. Wartości klienta w osobnych argumentach selektora (bez powłoki), zmienne nie trafiają do dziennika zdarzeń. Subkonto: FILES_MANAGE. D3 w wezel.csv. | 2026-09-30 D3 t1: 30.09: „Utwórz aplikację” (Node.js, d3.hvln.pl/nodetest) → „zmienne środowiskowe są niepoprawne” dla każdej aplikacji: agent ucinał końcowe „=” base64 (IFS='=' read) — to samo psuło klucze SSH → 4569ee5. Retest po wdrożeniu. | 2026-10-01 D3 t1: 01.10 po 4569ee5: Node.js d3.hvln.pl/nodetest — tworzenie, „Zależności” (Express 5.2.1 z package.json), zmienne środowiskowe, zatrzymaj/uruchom, restart, usuń działają. „Edytuj” → surowy błąd selektora (pełna wersja zamiast głównej) → d284195, retest. | 01.10 na t1 z panelu: utwórz, zależności, zmienne, zatrzymaj/uruchom, restart, edytuj, usuń — Node (Express) i Python (Flask) działają.
A38: B-09 | B38: B | C38: Aplikacje Python | D38: TAK | E38: TAK | F38: CZĘŚĆ | G38: CZĘŚĆ | H38: CZĘŚĆ | I38: DZIAŁA | J38: ops/scripts/node-app-selector.sh (zadanie APP_SELECTOR); subscriptions/app-selector.service.ts; services.controller.ts :id/hosting-apps; client-panel components/hosting/AplikacjeSelektorPanel.tsx (zakładka Aplikacje); node-hosting-profile.sh (alt-nodejs/alt-python + selektory włączone); testy test/aplikacje-selektor.spec.ts, app-selector.service.spec.ts | K38: PARYTET | L38: NISKA | M38: L | N38: 2026-09-25 KOD (D2): CloudLinux Selector wg oficjalnej dokumentacji (docs.cloudlinux.com → Command-line tools → Node.js/Python Selector; instalacja DirectAdmin: alt-nodejs/alt-python, lvemanager lve-utils alt-python-virtualenv alt-mod-passenger, --selector-status enabled). Zakładka Aplikacje → „Aplikacje Node.js i Python”: utwórz (język, wersja z serwera, domena + ścieżka, katalog poza public_html, plik startowy, obiekt WSGI, zmienne środowiskowe), edytuj (wersja, plik startowy, zmienne), uruchom/zatrzymaj/restart, zależności (npm install / pip -r requirements.txt), usuń. Wartości klienta w osobnych argumentach selektora (bez powłoki), zmienne nie trafiają do dziennika zdarzeń. Subkonto: FILES_MANAGE. D3 w wezel.csv. | 2026-09-30 D3 t1: 30.09: ten sam błąd co B-08 (base64 zmiennych bez końcowego „=”) → 4569ee5. Retest po wdrożeniu. | 2026-10-01 D3 t1: 01.10: Python dawał 503 (brak lswsgi: 3552440 profil, 972a40e bez wersji bez lswsgi — 3.14), potem 500 (passenger_wsgi.py jako plik startowy ładował sam siebie → 39df336). Z app.py: d3.hvln.pl/flask — Flask 3.1.3 z requirements.txt przez „Zależności”, restart działają. Retest „Edytuj” po d284195. | 01.10 na t1 z panelu: utwórz, zależności, zmienne, zatrzymaj/uruchom, restart, edytuj, usuń — Node (Express) i Python (Flask) działają. | 2026-10-03: profil instaluje brakujący alt-pythonXY-wsgi-lsapi (skrypt LSWS ma listę wersji do 3.13); t1: python314 dostał lswsgi, profil „[OK] Python przez LiteSpeed (lswsgi)”, WARN=0. Bez pakietu wersja jest wyłączana w selektorze (cloudlinux-selector disable-version).
A39: B-10 | B39: B | C39: Aplikacje Ruby | D39: TAK | E39: TAK | F39: NIE | G39: NIE | H39: NIE | I39: BRAK | J39: — | K39: POZA ZAKRESEM | L39: NISKA | M39: — | N39: rynek PL tego nie oczekuje
A40: B-11 | B40: B | C40: Wymuszenie HTTPS | D40: TAK | E40: TAK | F40: TAK | G40: TAK | H40: TAK | I40: DZIAŁA | J40: WebToolsTab.tsx:120 | K40: PARYTET | L40: — | M40: —
A41: B-12 | B41: B | C41: Kanonizacja www / non-www | D41: TAK | E41: TAK | F41: TAK | G41: TAK | H41: TAK | I41: DZIAŁA | J41: WebToolsTab.tsx:124 | K41: PARYTET | L41: — | M41: —
A42: B-13 | B42: B | C42: Przekierowania 301/302 z panelu | D42: TAK | E42: TAK | F42: TAK | G42: TAK | H42: TAK | I42: DZIAŁA | J42: WebToolsTab.tsx:143; D3 t1 (d3.hvln.pl) 29.09: 301 /verris-test-301 dodane z panelu → przekierowanie działa, usunięte z panelu → 404 | K42: PARYTET | L42: — | M42: —
A43: B-14 | B43: B | C43: Ochrona przed hotlinkingiem | D43: TAK | E43: TAK | F43: CZĘŚĆ | G43: CZĘŚĆ | H43: NIE | I43: DZIAŁA | J43: WebToolsTab.tsx:185 | K43: PRZEWAGA | L43: — | M43: —
A44: B-15 | B44: B | C44: Blokowanie adresów IP | D44: TAK | E44: TAK | F44: TAK | G44: CZĘŚĆ | H44: TAK | I44: DZIAŁA | J44: WebToolsTab.tsx:198 | K44: PARYTET | L44: — | M44: —
A45: B-16 | B45: B | C45: Ochrona katalogu hasłem (.htpasswd) | D45: TAK | E45: TAK | F45: TAK | G45: CZĘŚĆ | H45: TAK | I45: DZIAŁA | J45: WebToolsTab.tsx:91 | K45: PARYTET | L45: — | M45: —
A46: B-17 | B46: B | C46: Własne strony błędów | D46: TAK | E46: TAK | F46: TAK | G46: CZĘŚĆ | H46: TAK | I46: DZIAŁA | J46: ops/scripts/node-htaccess.sh; subscriptions/htaccess.service.ts; HtaccessPanel.tsx (strona → PHP i serwer) | K46: PARYTET | L46: NISKA | M46: S | N46: 2026-09-24: KOD (D2) + skrypt sprawdzony lokalnie — własne strony błędów 403/404/500 (ErrorDocument, ścieżka w witrynie walidowana w API i w skrypcie). Panel zarządza tylko blokiem „# BEGIN Verris” na początku public_html/.htaccess (reguły WordPressa i klienta zostają), plik czyta i zapisuje klient (dowiązanie → odmowa), po zapisie kontrola strony i przy 5xx powrót poprzedniego pliku. OTWARTE do D3 (sprint 21): Apache/LiteSpeed na węźle. | 2026-09-24 SKALA DOWODU (decyzja PM): funkcja bez pieniędzy, danych klienta i dostępu — D2 (test w CI) wystarcza do „zrobione”, więc werdykt PARYTET. Stan zostaje CZĘŚCIOWE do testu na węźle (audyt/dane/wezel.csv). | 2026-09-30 D3 t1: 30.09 test2.d3.hvln.pl: w panelu „Własne strony błędów” 404 → /404.html; zadanie .htaccess zakończone, nieistniejąca ścieżka zwraca status 404 z własną treścią. | 2026-10-06 D3 t1: przy braku własnej strony odwiedzający widział domyślną stronę serwera „Proudly powered by LiteSpeed”; f5c79c5 — profil węzła ustawia strony 403/404/500/503 Verris (httpd-includes.conf + ErrorDocument, .htaccess klienta ma pierwszeństwo). Do potwierdzenia na t1 po profilu. | 2026-10-06 D3 NA ŻYWO: serwerowe strony błędów Verris (ErrorDocument w CUSTOM.4.pre, 170028e) — d3.hvln.pl/<brak> zwraca 404 ze stroną Verris; profil meldował fałszywy FAIL (sprawdzał na 127.0.0.1) → cf87d80; wygląd w marce Verris → adb7778. | 2026-10-06 wieczór: profil t1 OK=65 FAIL=0 ([OK] strony błędów — sprawdzenie na IP konta), d3.hvln.pl/<brak> pokazuje stronę 404 w marce Verris. | 2026-10-08 profil t1 OK=65: strony błędów 403/404/500/502/503/504 w marce Verris (cd2143b9); o05.d3.hvln.pl/<brak> → 404 Verris bez śladów serwera.
A47: B-18 | B47: B | C47: Menedżer indeksowania katalogu | D47: TAK | E47: TAK | F47: TAK | G47: b.d. | H47: NIE | I47: DZIAŁA | J47: ops/scripts/node-htaccess.sh; subscriptions/htaccess.service.ts; HtaccessPanel.tsx (strona → PHP i serwer); D3 t1 29.09 (panel klienta, d3.hvln.pl): lista plików „Ukryta” → /wp-includes/ zwraca 403 | K47: PARYTET | L47: NISKA | M47: S | N47: 2026-09-24: KOD (D2) + skrypt sprawdzony lokalnie — lista plików w katalogu bez strony głównej: domyślnie / ukryta (Options -Indexes) / widoczna. Panel zarządza tylko blokiem „# BEGIN Verris” na początku public_html/.htaccess (reguły WordPressa i klienta zostają), plik czyta i zapisuje klient (dowiązanie → odmowa), po zapisie kontrola strony i przy 5xx powrót poprzedniego pliku. OTWARTE do D3 (sprint 21): Apache/LiteSpeed na węźle. | 2026-09-24 SKALA DOWODU (decyzja PM): funkcja bez pieniędzy, danych klienta i dostępu — D2 (test w CI) wystarcza do „zrobione”, więc werdykt PARYTET. Stan zostaje CZĘŚCIOWE do testu na węźle (audyt/dane/wezel.csv).
A48: B-19 | B48: B | C48: Kreator stron WWW | D48: TAK | E48: TAK | F48: CZĘŚĆ | G48: CZĘŚĆ | H48: TAK | I48: BRAK | J48: SiteBuilderTab.tsx usunięty 2026-09-25 | K48: LUKA | L48: NISKA | M48: M | N48: DECYZJA 2026-09-24: kreator usunięty z cennika verris.pl („Menedżer plików w panelu” zamiast „Kreator stron i menedżer plików”) — obietnica zgodna z produktem; kod zostaje wyłączony, powrót jako osobna funkcja po starcie. | kod napisany i zakomentowany — decyzja: dokończyć albo usunąć | DECYZJA WŁAŚCICIELA 2026-09-25: wyłączony kod usunięty (1612 linii bez importów i bez API); kreator wraca po starcie jako nowa funkcja.
A49: C-01 | B49: C | C49: Menedżer plików — lista katalogu | D49: TAK | E49: TAK | F49: TAK | G49: TAK | H49: TAK | I49: DZIAŁA | J49: files.controller.ts:27; D3 t1 (d3.hvln.pl) 29.09: lista katalogu domowego z datami i rozmiarami | K49: PARYTET | L49: — | M49: —
A50: C-02 | B50: C | C50: Podgląd i edycja pliku tekstowego | D50: TAK | E50: TAK | F50: TAK | G50: TAK | H50: TAK | I50: DZIAŁA | J50: files.controller.ts:36,61; D3 t1 (d3.hvln.pl) 29.09: edycja pliku .php w edytorze panelu, zapis działa | K50: PARYTET | L50: — | M50: —
A51: C-03 | B51: C | C51: Tworzenie katalogu | D51: TAK | E51: TAK | F51: TAK | G51: TAK | H51: TAK | I51: DZIAŁA | J51: files.controller.ts:71; D3 t1 (d3.hvln.pl) 29.09: nowy folder z panelu | K51: PARYTET | L51: — | M51: —
A52: C-04 | B52: C | C52: Tworzenie pliku | D52: TAK | E52: TAK | F52: TAK | G52: TAK | H52: TAK | I52: DZIAŁA | J52: files.controller.ts:61; D3 t1 (d3.hvln.pl) 29.09: nowy plik verris-cron-test.php z panelu + edycja i zapis treści | K52: PARYTET | L52: — | M52: —
A53: C-05 | B53: C | C53: Zmiana nazwy pliku/katalogu | D53: TAK | E53: TAK | F53: TAK | G53: TAK | H53: TAK | I53: DZIAŁA | J53: files.controller.ts:81; D3 t1 (d3.hvln.pl) 29.09 FAIL: zmiana nazwy → „Wewnętrzny błąd serwera” (DA 1.710: old = sama nazwa, nie pełna ścieżka; sprawdzone na t1); poprawka 3434c1a czeka na wdrożenie; D3 t1 (d3.hvln.pl) 29.09 po wdrożeniu: zmiana nazwy verris-r1.txt → verris-r2.txt z panelu — „Zmieniono nazwę”, plik pod nową nazwą (3434c1a: old = sama nazwa) | K53: PARYTET | L53: — | M53: —
A54: C-06 | B54: C | C54: Usuwanie plików (także zaznaczonych) | D54: TAK | E54: TAK | F54: TAK | G54: TAK | H54: TAK | I54: DZIAŁA | J54: files.controller.ts:91; D3 t1 (d3.hvln.pl) 29.09 FAIL: „Usuń zaznaczone” → komunikat sukcesu, pliki zostają (DA 1.710 wymaga selectN = pełna ścieżka; sprawdzone na t1: nazwa → bez zmian, pełna ścieżka → usunięty); poprawka 464dd72 (SDK) czeka na wdrożenie; retest; 29.09: usuwanie pełnymi ścieżkami sprawdzone na t1 bezpośrednio w DA (6 elementów naraz); retest z panelu po wdrożeniu 347e8ae; D3 t1 (d3.hvln.pl) 29.09 po wdrożeniu: zaznaczenie 2 plików (verris-r2.tar.gz, verris-r2.txt) → Usuń → potwierdzenie; API DA: pliki usunięte (347e8ae: CMD_API_FILE_MANAGER + pełne ścieżki) | K54: PARYTET | L54: — | M54: —
A55: C-07 | B55: C | C55: Kopiowanie plików | D55: TAK | E55: TAK | F55: TAK | G55: TAK | H55: TAK | I55: DZIAŁA | J55: files.controller.ts:101; D3 t1 (d3.hvln.pl) 29.09: ten sam format zaznaczenia co C-06 (schowek DA) — poprawka razem z C-06; D3 do potwierdzenia; D3 t1 (d3.hvln.pl) 29.09 po wdrożeniu: kopiowanie verris-a.txt do folderu z panelu — plik w obu miejscach | K55: PARYTET | L55: — | M55: —
A56: C-08 | B56: C | C56: Przenoszenie plików | D56: TAK | E56: TAK | F56: TAK | G56: TAK | H56: TAK | I56: DZIAŁA | J56: files.controller.ts:111; D3 t1 (d3.hvln.pl) 29.09: jak C-07; D3 t1 (d3.hvln.pl) 29.09 po wdrożeniu: przeniesienie verris-b.txt do folderu — zniknął z katalogu źródłowego | K56: PARYTET | L56: — | M56: —
A57: C-09 | B57: C | C57: Zmiana uprawnień (chmod) | D57: TAK | E57: TAK | F57: TAK | G57: TAK | H57: TAK | I57: DZIAŁA | J57: files.controller.ts:131; D3 t1 (d3.hvln.pl) 29.09: chmod zaznaczonych — ten sam format co C-06; D3 do potwierdzenia po wdrożeniu; D3 t1 (d3.hvln.pl) 29.09 po wdrożeniu: chmod 600 z panelu, DA pokazuje permission=600 | K57: PARYTET | L57: — | M57: —
A58: C-10 | B58: C | C58: Rozpakowanie archiwum | D58: TAK | E58: TAK | F58: TAK | G58: TAK | H58: TAK | I58: DZIAŁA | J58: files.controller.ts:121 | K58: PARYTET | L58: — | M58: —
A59: C-11 | B59: C | C59: Spakowanie do archiwum | D59: TAK | E59: TAK | F59: TAK | G59: TAK | H59: TAK | I59: DZIAŁA | J59: 2026-09-23 D1: POST /services/:id/files/compress → files.service compress (nazwa archiwum walidowana) → SDK compressEntries (schowek DA + action=compress) + audyt HOSTING_FILE_COMPRESSED; UI menedżera plików „Spakuj…” dla zaznaczonych; D3 t1 (d3.hvln.pl) 29.09: archiwum powstaje, ale panel mówi „nie udało się” (stara CMD_FILE_MANAGER zwraca 500 po wykonaniu) — poprawka 347e8ae (CMD_API_FILE_MANAGER); D3 t1 (d3.hvln.pl) 29.09 po wdrożeniu: Spakuj z panelu → „Spakowano do archiwum”, verris-r2.tar.gz w katalogu (347e8ae: bez fałszywego błędu 500 starego endpointu) | K59: PARYTET | L59: — | M59: S | N59: standard we wszystkich panelach | OTWARTE do D3 (PB-21): format action=compress na żywym DA.
A60: C-12 | B60: C | C60: Upload pliku | D60: TAK | E60: TAK | F60: TAK | G60: TAK | H60: TAK | I60: DZIAŁA | J60: files.controller.ts:141 | K60: PARYTET | L60: — | M60: —
A61: C-13 | B61: C | C61: Pobranie pliku | D61: TAK | E61: TAK | F61: TAK | G61: TAK | H61: TAK | I61: DZIAŁA | J61: files.controller.ts:45 | K61: PARYTET | L61: — | M61: —
A62: C-14 | B62: C | C62: Wyszukiwanie plików | D62: TAK | E62: TAK | F62: CZĘŚĆ | G62: CZĘŚĆ | H62: TAK | I62: DZIAŁA | J62: ops/scripts/node-file-search.sh; subscriptions/file-search.service.ts; FileSearchPanel.tsx (strona → Pliki); D3 t1 29.09 (panel klienta, d3.hvln.pl): szukanie nazwa „config” + tekst „DB_NAME” → 3 pliki (wp-config.php, wp-config-sample.php, wp-admin/setup-config.php) | K62: PARYTET | L62: NISKA | M62: S | N62: 2026-09-24: KOD (D2) + skrypt sprawdzony lokalnie — szukanie w public_html domeny po fragmencie nazwy i/lub tekście w treści (grep -F, tylko pliki tekstowe do 5 MB), szuka klient (runuser, bez podążania za dowiązaniami), do 500 wyników, limit 90 s z komunikatem. Przydatne też przy infekcji (np. „eval(base64_decode”). OTWARTE do D3 (sprint 21): czas na dużych stronach w CageFS. | 2026-09-24 SKALA DOWODU (decyzja PM): funkcja bez pieniędzy, danych klienta i dostępu — D2 (test w CI) wystarcza do „zrobione”, więc werdykt PARYTET. Stan zostaje CZĘŚCIOWE do testu na węźle (audyt/dane/wezel.csv).
A63: C-15 | B63: C | C63: Podgląd zajętości katalogów (disk usage) | D63: TAK | E63: TAK | F63: TAK | G63: CZĘŚĆ | H63: TAK | I63: DZIAŁA | J63: ops/scripts/node-disk-usage.sh (zadanie DISK_USAGE, du jako klient, 2 poziomy), subscriptions/disk-usage.service.ts, services.controller.ts :id/hosting-disk-usage, client-panel components/hosting/DiskUsagePanel.tsx (Zużycie zasobów → Co zajmuje miejsce); test disk-usage.service.spec.ts; D3 t1 29.09 (panel klienta, d3.hvln.pl): „Co zajmuje miejsce” → razem 271,5 MB / 5821 plików, podział na domains, backups, poczta, eksporty baz itd. (2 poziomy) | K63: PARYTET | L63: ŚREDNIA | M63: S | N63: 2026-09-24: KOD (D2) + skrypt sprawdzony lokalnie — rozmiar i liczba plików w katalogach konta (drzewo 2 poziomów, opisy: poczta, kopie, pliki stron), liczone na żądanie. OTWARTE do D3 (sprint 21): czas du na dużych kontach, CageFS. | częste źródło ticketów „skończyło się miejsce” | 2026-09-24 SKALA DOWODU (decyzja PM): funkcja bez pieniędzy, danych klienta i dostępu — D2 (test w CI) wystarcza do „zrobione”, więc werdykt PARYTET. Stan zostaje CZĘŚCIOWE do testu na węźle (audyt/dane/wezel.csv).
A64: C-16 | B64: C | C64: Konto FTP — utworzenie | D64: TAK | E64: TAK | F64: TAK | G64: TAK | H64: TAK | I64: DZIAŁA | J64: services.controller.ts:406 | K64: PARYTET | L64: — | M64: —
A65: C-17 | B65: C | C65: Konto FTP — usunięcie | D65: TAK | E65: TAK | F65: TAK | G65: TAK | H65: TAK | I65: DZIAŁA | J65: services.controller.ts:415; D3 t1 (d3.hvln.pl) 29.09: DA 1.710 zwraca listę FTP jako login@domena=ścieżka (nie user0/path0) — dodatkowe konta niewidoczne w panelu, więc bez usuwania i zmiany hasła; poprawka bcce42d czeka na wdrożenie; D3 na koncie dodatkowym | K65: PARYTET | L65: ŚREDNIA | M65: — | N65: | 2026-10-02 D3: tworzenie działa (po 9e362ed), usunięcie z panelu dawało fałszywy sukces (select0=login@domena) → poprawka 2f0d9a2 (select0=login + kontrola listy); retest po wdrożeniu. | 2026-10-02 D3: 02.10 t1 (po 2f0d9a2): „Usuń konto FTP” przy d3test@d3.hvln.pl → „Konto FTP usunięte”, po odświeżeniu „Brak dodatkowych kont FTP” (wcześniej fałszywy sukces: select0=login@domena, DA OK bez efektu). Tworzenie (po 9e362ed) i zmiana hasła sprawdzone tego samego dnia (C-18).
A66: C-18 | B66: C | C66: Konto FTP — zmiana hasła | D66: TAK | E66: TAK | F66: TAK | G66: TAK | H66: TAK | I66: DZIAŁA | J66: 2026-09-23 D1: POST /services/:id/hosting-ftp/:username/password (ZmienHasloFtpDto) → directadmin.service changeHostingFtpPassword (action=modify, katalog zachowany) + audyt HOSTING_FTP_PASSWORD_CHANGED; UI FtpTab — kluczyk przy koncie; test servers/zmiana-hasla-ftp.spec.ts | K66: PARYTET | L66: WYSOKA | M66: S | N66: brak jakiejkolwiek ścieżki edycji istniejącego konta | Przy okazji body tworzenia konta FTP dostało klasę DTO (login, hasło, katalog bez „..”). OTWARTE do D3 (PB-21): format action=modify na żywym DA. | 2026-10-02 D3: 02.10 t1 (po 9e362ed — tworzenie konta FTP wysyłało pole path zamiast wymaganego type, panel mówił „słabe hasło”): panel → FTP i SSH → konto d3test@d3.hvln.pl z hasłem z generatora → „Konto FTP utworzone”, katalog /home/ovsekucx/domains/d3.hvln.pl/; „Nowe hasło” → „Hasło FTP zmienione”, katalog bez zmian; logowanie nowym hasłem z Maca: curl --ssl-reqd ftp://t1.verris.pl/ → lista katalogu domeny (public_html, public_ftp, logs, stats, private_html).
A67: C-19 | B67: C | C67: Konto FTP — limit powierzchni (quota) | D67: TAK | E67: TAK | F67: TAK | G67: CZĘŚĆ | H67: NIE | I67: BRAK | J67: — | K67: POZA ZAKRESEM | L67: NISKA | M67: S | N67: | 2026-09-25 SPRAWDZONE W DOKUMENTACJI: DirectAdmin nie ma limitu powierzchni per konto FTP (docs.directadmin.com → FTP; konta FTP dzielą limit konta hostingowego, który panel pokazuje). Do decyzji właściciela: POZA ZAKRESEM (limit konta wystarcza) albo własne rozwiązanie poza DA. | DECYZJA WŁAŚCICIELA 2026-09-25: poza zakresem — DirectAdmin nie ma limitu per konto FTP; obowiązuje limit konta hostingowego (widoczny w panelu).
A68: C-20 | B68: C | C68: FTP anonimowy | D68: TAK | E68: TAK | F68: TAK | G68: NIE | H68: NIE | I68: BRAK | J68: — | K68: POZA ZAKRESEM | L68: NISKA | M68: — | N68: funkcja schyłkowa, ryzyko nadużyć
A69: C-21 | B69: C | C69: Dostęp SSH | D69: TAK | E69: TAK | F69: TAK | G69: TAK | H69: TAK | I69: DZIAŁA | J69: ops/scripts/node-ssh-access.sh (zadanie SSH_ACCESS), subscriptions/ssh-access.service.ts, services.controller.ts :id/hosting-ssh(/keys), client-panel components/hosting/SshPanel.tsx (FTP → Dostęp SSH); test ssh-access.service.spec.ts; D3 t1 (d3.hvln.pl) 29.09 po wdrożeniu (panel klienta): włączenie SSH z panelu → DA ssh=ON; logowania z zewnątrz nie sprawdziłem (brak ruchu TCP/22 ze środowiska testowego) — do potwierdzenia przez właściciela; D3 t1 29.09 13:58: logowanie kluczem ed25519 wgranym w panelu (zakładka FTP i SSH) jako ovsekucx@t1.verris.pl:22 działa; konto w klatce CageFS (ls /home → tylko ovsekucx, /etc/passwd 23 linie zamiast systemowego) | K69: PARYTET | L69: WYSOKA | M69: M | N69: 2026-09-24: KOD (D2) + skrypt sprawdzony lokalnie — włączanie/wyłączanie SSH z panelu tylko w klatce CageFS (bez niej odmowa), user.conf + powłoka + AllowUsers spójnie. DECYZJA WŁAŚCICIELA 2026-09-24: SSH w klatce na start. OTWARTE do D3 (sprint 21): CageFS na węźle, reload sshd, logowanie kluczem i hasłem, ochrona przed zgadywaniem haseł (fail2ban/CSF w profilu węzła). | klient widzi status, nie może włączyć | 2026-10-01 D3 t1: 01.10: fail2ban z utwardzania usunął CustomBuild 29.09 (options.conf fail2ban=no), BFM bez block_ip.sh nie blokuje — węzeł bez blokowania zgadywania haseł → 073123f (fail2ban przez CustomBuild). Retest po da build fail2ban.
A70: C-22 | B70: C | C70: Zarządzanie kluczami SSH konta hostingowego | D70: TAK | E70: TAK | F70: TAK | G70: CZĘŚĆ | H70: TAK | I70: DZIAŁA | J70: ops/scripts/node-ssh-access.sh (zadanie SSH_ACCESS), subscriptions/ssh-access.service.ts, services.controller.ts :id/hosting-ssh(/keys), client-panel components/hosting/SshPanel.tsx (FTP → Dostęp SSH); test ssh-access.service.spec.ts; D3 t1 (d3.hvln.pl) 29.09 po wdrożeniu (panel klienta): klucz publiczny z panelu → blok Verris w ~/.ssh/authorized_keys; logowanie kluczem do potwierdzenia (jak C-21); D3 t1 (d3.hvln.pl) 29.09 po wdrożeniu 13:00 (panel klienta): klucz testowy usunięty z panelu (blok Verris w authorized_keys aktualizowany); D3 t1 29.09 13:58: logowanie kluczem ed25519 wgranym w panelu (zakładka FTP i SSH) jako ovsekucx@t1.verris.pl:22 działa; konto w klatce CageFS (ls /home → tylko ovsekucx, /etc/passwd 23 linie zamiast systemowego) | K70: PARYTET | L70: WYSOKA | M70: M | N70: 2026-09-24: KOD (D2) + skrypt sprawdzony lokalnie — klucze w bloku Verris ~/.ssh/authorized_keys (zapis jako klient, walidacja ssh-keygen, bez opcji), klucze klienta poza blokiem zostają. DECYZJA WŁAŚCICIELA 2026-09-24: SSH w klatce na start. OTWARTE do D3 (sprint 21): CageFS na węźle, reload sshd, logowanie kluczem i hasłem, ochrona przed zgadywaniem haseł (fail2ban/CSF w profilu węzła). | klucze są tylko dla VPS, nie dla hostingu
A71: C-23 | B71: C | C71: Terminal SSH w przeglądarce | D71: TAK | E71: NIE | F71: NIE | G71: NIE | H71: CZĘŚĆ | I71: BRAK | J71: — | K71: POZA ZAKRESEM | L71: NISKA | M71: L | N71: żaden hosting PL tego nie daje
A72: C-24 | B72: C | C72: WebDAV / Web Disk | D72: TAK | E72: TAK | F72: NIE | G72: NIE | H72: NIE | I72: BRAK | J72: — | K72: POZA ZAKRESEM | L72: NISKA | M72: — | N72: Protokół schyłkowy — żaden z pięciu badanych hostingów PL go nie wystawia, a menedżer plików i SFTP pokrywają ten sam scenariusz.
A73: C-25 | B73: C | C73: Klonowanie repozytorium Git z panelu | D73: TAK | E73: TAK | F73: CZĘŚĆ | G73: NIE | H73: TAK | I73: DZIAŁA | J73: ops/scripts/node-git-deploy.sh (zadanie GIT_DEPLOY: klucz ed25519 ~/.ssh/verris_deploy, git clone --depth 50 z odłożeniem dotychczasowych plików, pull --ff-only, HEAD w wyniku; jako klient), subscriptions/git-deploy.service.ts, :id/hosting-git(/key|/clone|/pull), panel GitRepoPanel.tsx (Deploy (Git) → Repozytorium strony); test git-deploy.service.spec.ts; D3 t1 29.09 (panel klienta, d3.hvln.pl): „Sklonuj” https://github.com/WordPress/hello-dolly.git do public_html/git-test → gotowe, HEAD 5a6f8b3; pliki serwowane, katalog .git zwraca 403 | K73: PARYTET | L73: ŚREDNIA | M73: M | N73: 2026-09-24: KOD (D2) + skrypt sprawdzony lokalnie (klucz 0600 jako klient, pull z HEAD, odmowy: file://, gałąź „--…”, katalog z „..”). OTWARTE do D3 (sprint 21): git i ssh w klatce CageFS, klon z GitHuba kluczem wdrożeniowym. | „Deploy” to wyłącznie cron z git pull
A74: C-26 | B74: C | C74: Deploy z repozytorium (pull na żądanie) | D74: TAK | E74: TAK | F74: CZĘŚĆ | G74: NIE | H74: TAK | I74: DZIAŁA | J74: ops/scripts/node-git-deploy.sh (zadanie GIT_DEPLOY: klucz ed25519 ~/.ssh/verris_deploy, git clone --depth 50 z odłożeniem dotychczasowych plików, pull --ff-only, HEAD w wyniku; jako klient), subscriptions/git-deploy.service.ts, :id/hosting-git(/key|/clone|/pull), panel GitRepoPanel.tsx (Deploy (Git) → Repozytorium strony); test git-deploy.service.spec.ts; harmonogram: services.controller.ts:717, directadmin.service.ts createDeployJob; D3 t1 29.09 (panel klienta, d3.hvln.pl): „Pobierz zmiany teraz” dla git-test → pobranie zmian gotowe, HEAD w wyniku | K74: PARYTET | L74: ŚREDNIA | M74: M | N74: 2026-09-24: dołożone „Pobierz zmiany teraz”, klucz wdrożeniowy i wynik (HEAD / błąd) w panelu — zostają webhook (C-27) i logi builda. | tylko harmonogram cron; brak „uruchom teraz”, kluczy deploy, webhooka, logów
A75: C-27 | B75: C | C75: Webhook deploy z GitHuba | D75: CZĘŚĆ | E75: TAK | F75: NIE | G75: NIE | H75: TAK | I75: DZIAŁA | J75: subscriptions/git-webhook.controller.ts (POST /hooks/git/:token, bez logowania, limit), GitDeployService.utworzWebhook/usunWebhook/wyzwolWebhook (model GitWebhook: tylko skrót tokenu), :id/hosting-git-webhook(/delete), GitRepoPanel.tsx (adres pokazany raz, lista z datą ostatniego wywołania); test git-deploy.service.spec.ts | K75: PARYTET | L75: NISKA | M75: M | N75: 2026-09-24: KOD (D2) — webhook GitHub/GitLab/Bitbucket kolejkuje git pull w katalogu strony; treść żądania nie jest czytana (każde wywołanie = pobierz zmiany), więc podrobiony payload nic nie zmieni. OTWARTE do D3 (sprint 21) razem z C-25. | 2026-10-04: D3 na t1 (d3.hvln.pl) — prywatne repo GitHub: klucz wdrożeniowy z panelu → dodany jako deploy key (tylko odczyt) → klon do public_html/payload (c681f57); webhook z panelu dodany w GitHubie, push → „pobranie zmian (webhook) · gotowe”, HEAD 615cdbe. Po drodze: egress węzła wpuszcza TCP/22 tylko dla roota — klon git@github.com wisiał i kończył się „sprawdź klucz”; poprawka 33e4722 (SSH na 443: ssh.github.com/altssh.gitlab.com/altssh.bitbucket.org, klucz i adres zapisane w repo dla crona, ConnectTimeout, komunikat o porcie 22). .git i pliki z kropką → 403 z WWW. Panel: „Odśwież” nie wczytywał sekcji repo — poprawione.
A76: C-28 | B76: C | C76: Composer / narzędzia CLI przez SSH | D76: TAK | E76: TAK | F76: TAK | G76: TAK | H76: TAK | I76: DZIAŁA | J76: zależne od C-21 | K76: PARYTET | L76: ŚREDNIA | M76: M | N76: 2026-09-24: odblokowane przez C-21 (SSH w klatce z panelu) — do potwierdzenia na węźle. | dziedziczy ograniczenie SSH | WYCENA 2026-09-19: krytycznosc i naklad uzupelnione przy wznowieniu. Pozycje przepisane 2026-08-28 w ramach X-49 zostaly bez wyceny, przez co nie liczyly sie do budzetu godzin i nie stały w zadnym sprincie. Podstawa wyceny: Composer i narzedzia CLI przez SSH — wymaga uzgodnienia z limitami LVE i obrazem kontenera klienta. | 2026-10-02 D3: SSH w CageFS działa (wp), ale „composer: command not found” → profil instaluje oficjalny composer.phar z sumą SHA-256 (b9370db); retest po przebiegu profilu. | 2026-10-03: D3 na t1 — composer --version przez SSH (2.10.3, PHP 8.3) i wp --version działają w CageFS; SSH przetrwało przebieg profilu (synchronizacja pakietów nie nadpisuje istniejących — a25b3cc).
A77: D-01 | B77: D | C77: Lista baz MySQL/MariaDB | D77: TAK | E77: TAK | F77: TAK | G77: TAK | H77: TAK | I77: DZIAŁA | J77: services.controller.ts:323; D3 t1 (d3.hvln.pl) 29.09 FAIL: baza WordPressa istnieje, panel „Brak baz” — DA 1.710 zwraca list[]=nazwa; poprawka bcce42d (SDK daPayloadToParams) czeka na wdrożenie; retest; D3 t1 (d3.hvln.pl) 29.09 08:3x po wdrożeniu: lista pokazuje bazę WordPressa (ovsekucx_wp8664) | K77: PARYTET | L77: — | M77: — | N77: + realny silnik i wersja z węzła
A78: D-02 | B78: D | C78: Utworzenie bazy z użytkownikiem | D78: TAK | E78: TAK | F78: TAK | G78: TAK | H78: TAK | I78: DZIAŁA | J78: services.controller.ts:328 | K78: PARYTET | L78: — | M78: —
A79: D-03 | B79: D | C79: Usunięcie bazy | D79: TAK | E79: TAK | F79: TAK | G79: TAK | H79: TAK | I79: DZIAŁA | J79: services.controller.ts:341 | K79: PARYTET | L79: — | M79: —
A80: D-04 | B80: D | C80: Dodatkowy użytkownik bazy — utworzenie | D80: TAK | E80: TAK | F80: TAK | G80: TAK | H80: TAK | I80: DZIAŁA | J80: services.controller.ts — POST /services/:id/hosting-db-users; serwis directadmin.service.ts:1900 | K80: PARYTET | L80: — | M80: S | N80: Nie było to martwe UI, tylko niedokończona praca z 25–26.07 — brakowało samego kontrolera. Zamknięte 2026-08-21 (commit 6f2833d). Strażnik: apps/api/src/test/ui-routes-coverage.spec.ts porównuje wszystkie wywołania apiFetch z panelu ze wszystkimi trasami API — nawrót tej klasy błędu zapala test.
A81: D-05 | B81: D | C81: Użytkownik bazy — usunięcie | D81: TAK | E81: TAK | F81: TAK | G81: TAK | H81: TAK | I81: DZIAŁA | J81: services.controller.ts — POST /services/:id/hosting-db-users/remove; serwis directadmin.service.ts:1925 | K81: PARYTET | L81: — | M81: S | N81: Zamknięte 2026-08-21 (commit 6f2833d). Strażnik: apps/api/src/test/ui-routes-coverage.spec.ts porównuje wszystkie wywołania apiFetch z panelu ze wszystkimi trasami API — nawrót tej klasy błędu zapala test.
A82: D-06 | B82: D | C82: Użytkownik bazy — zmiana hasła | D82: TAK | E82: TAK | F82: TAK | G82: TAK | H82: TAK | I82: DZIAŁA | J82: services.controller.ts — POST /services/:id/hosting-db-users/password; serwis directadmin.service.ts:1945 | K82: PARYTET | L82: — | M82: S | N82: Zamknięte 2026-08-21 (commit 6f2833d). Strażnik: apps/api/src/test/ui-routes-coverage.spec.ts porównuje wszystkie wywołania apiFetch z panelu ze wszystkimi trasami API — nawrót tej klasy błędu zapala test.
A83: D-07 | B83: D | C83: Użytkownik bazy — lista | D83: TAK | E83: TAK | F83: TAK | G83: TAK | H83: TAK | I83: DZIAŁA | J83: services.controller.ts — GET /services/:id/hosting-db-users; D3 t1 (d3.hvln.pl) 29.09: lista użytkowników bazy (ovsekucx_wp8664, pełne uprawnienia) | K83: PARYTET | L83: — | M83: S | N83: Zamknięte 2026-08-21 (commit 6f2833d). Strażnik: apps/api/src/test/ui-routes-coverage.spec.ts porównuje wszystkie wywołania apiFetch z panelu ze wszystkimi trasami API — nawrót tej klasy błędu zapala test.
A84: D-08 | B84: D | C84: Nadawanie uprawnień użytkownikowi bazy | D84: TAK | E84: TAK | F84: TAK | G84: CZĘŚĆ | H84: TAK | I84: DZIAŁA | J84: ops/scripts/node-db-transfer.sh (privileges); db-transfer.service.ts zlecUprawnienia; DbUsers.tsx | K84: PARYTET | L84: ŚREDNIA | M84: S | N84: 2026-09-24: KOD (D2) + skrypt sprawdzony lokalnie na MariaDB 10.11 — przy każdym użytkowniku bazy wybór: pełne / odczyt i zapis danych / tylko odczyt. GRANT na węźle dla wszystkich hostów użytkownika (localhost i zdalne z D-09), obie formy nazwy bazy zdejmowane (DA nadaje bez ucieczki „_”), nadawane z ucieczką; baza i użytkownik tylko z prefiksem konta, zestaw z białej listy. Sprawdzone: „tylko odczyt” → INSERT odrzucony, SELECT działa. Panel pamięta ostatni zestaw ustawiony w panelu (zmiana w phpMyAdmin nie jest odczytywana). | 2026-09-29 D3 t1: po 66a685a i przeinstalowaniu agenta „Tylko odczyt” dla ovsekucx_test → SHOW GRANTS: SELECT, SHOW VIEW na ovsekucx_wp8664 (wcześniej ALL PRIVILEGES).
A85: D-09 | B85: D | C85: Zdalny dostęp do bazy (whitelist hostów) | D85: TAK | E85: TAK | F85: TAK | G85: CZĘŚĆ | H85: TAK | I85: DZIAŁA | J85: services.controller.ts:617,626; D3 t1 (d3.hvln.pl) 29.09: lista hostów (localhost), dodanie 192.0.2.10 i usunięcie z panelu | K85: PARYTET | L85: — | M85: —
A86: D-10 | B86: D | C86: phpMyAdmin — dostęp | D86: TAK | E86: TAK | F86: TAK | G86: TAK | H86: TAK | I86: DZIAŁA | J86: dostęp przez auto-logowanie z panelu (D-11: POST /services/:id/hosting-sso-url) — DatabasesTab | K86: PARYTET | L86: ŚREDNIA | M86: S | N86: dostępny, ale przez wyjście do DirectAdmina | 2026-09-23 PORZĄDKI: wpis „link do DA” sprzed D-11 (SSO, DZIAŁA od 2026-08-21) — dostęp jest z panelu bez wychodzenia do DirectAdmina.
A87: D-11 | B87: D | C87: phpMyAdmin — auto-logowanie (SSO) | D87: TAK | E87: TAK | F87: TAK | G87: TAK | H87: TAK | I87: DZIAŁA | J87: services.controller.ts — POST /services/:id/hosting-sso-url; directadmin.service.ts:1977; D3 t1 (d3.hvln.pl) 29.09 po wdrożeniu 13:00 (panel klienta): phpMyAdmin z panelu otwiera się jednorazowym skryptem /phpMyAdmin/sso/ na 443, bez sesji DirectAdmina (white label, ab64241) | K87: PARYTET | L87: — | M87: S | N87: Cichy fallback „Auto-logowanie niedostępne" (DatabasesTab.tsx:65) sprawiał, że nikt tego nie zgłaszał — dlatego strażnik tras jest ważniejszy niż pojedynczy test. Zamknięte 2026-08-21 (commit 6f2833d). Strażnik: apps/api/src/test/ui-routes-coverage.spec.ts porównuje wszystkie wywołania apiFetch z panelu ze wszystkimi trasami API — nawrót tej klasy błędu zapala test.
A88: D-12 | B88: D | C88: Import / eksport bazy z panelu | D88: TAK | E88: TAK | F88: TAK | G88: TAK | H88: TAK | I88: DZIAŁA | J88: ops/scripts/node-db-transfer.sh (zadanie DB_TRANSFER), subscriptions/db-transfer.service.ts, services.controller.ts :id/hosting-db-transfer|hosting-db-export|hosting-db-import, client-panel components/hosting/DbTransferPanel.tsx; testy db-transfer.service.spec.ts, agent-wezla-jedno-zrodlo.spec.ts; D3 t1 (d3.hvln.pl) 29.09 po wdrożeniu (panel klienta): eksport bazy WordPressa → plik .sql.gz 34 KB w verris-bazy; import tego pliku z potwierdzeniem → kopia przed importem + import, strona działa | K88: PARYTET | L88: — | M88: M | N88: 2026-09-24: KOD (D2) + skrypt sprawdzony lokalnie na MariaDB 10.11 — eksport .sql.gz do ~/verris-bazy, import z automatyczną kopią i tymczasowym użytkownikiem MySQL tylko do tej bazy (USE obcej bazy, baza „loginXnazwa” przez „_” w GRANT → odmowa; dowiązanie do pliku roota → „brak pliku”). ZNALEZISKO NAPRAWIONE przy okazji: kopie agenta w ops/scripts (onboarding węzła) nie przekazywały PHP_APPLY/APP_INSTALL/OFFSITE_RESTORE/FLEET_UPDATE, a runner dla nieznanego rodzaju uruchamiał profil hostingu; teraz jedno źródło + strażnik. OTWARTE do D3 (sprint 21, węzeł #1): przebieg na DirectAdmin/CloudLinux (runuser w CageFS, my.cnf DA). | standard u wszystkich 5 hostingów PL | 2026-10-06 D3 t1: eksport ovsekucx_wp0922 → import tego pliku (kopia sprzed importu w verris-bazy) → beta.d3.hvln.pl działa.
A89: D-13 | B89: D | C89: Kopia bazy na żądanie | D89: TAK | E89: TAK | F89: TAK | G89: TAK | H89: TAK | I89: DZIAŁA | J89: D-12: DbTransferPanel „Eksportuj bazę” (zadanie DB_TRANSFER export → ~/verris-bazy/<baza>-<czas>.sql.gz, pobranie z panelu); D3 t1 29.09 (panel klienta, d3.hvln.pl): eksport bazy w verris-bazy + pobranie przez /api/services/:id/files/download: 34 696 B, nagłówek gzip | K89: PARYTET | L89: ŚREDNIA | M89: S | N89: brak osobnej akcji „zrzuć bazę” | 2026-09-24: osobna akcja „zrzuć bazę” jest — to eksport z D-12 (plik .sql.gz na koncie, do pobrania z panelu), a import robi kopię przed nadpisaniem. Dane klienta → D3: OTWARTE do D3 (sprint 21) razem z D-12.
A90: D-14 | B90: D | C90: PostgreSQL | D90: TAK | E90: TAK | F90: CZĘŚĆ | G90: CZĘŚĆ | H90: CZĘŚĆ | I90: DZIAŁA | J90: ops/scripts/node-pgsql.sh (zadanie PGSQL, migracja 20260925210000); subscriptions/pgsql.service.ts; services.controller.ts :id/hosting-pgsql; client-panel PgsqlPanel (zakładka Bazy danych); node-hosting-profile.sh (PostgreSQL 16 z AppStream, localhost, scram-sha-256); test pgsql.service.spec.ts | K90: PARYTET | L90: NISKA | M90: L | N90: 2 z 5 hostingów PL | DECYZJA WŁAŚCICIELA 2026-09-25: PostgreSQL robimy teraz (kod + instalacja wg dokumentacji, D3 na węźle testowym). | ZROBIONE W KODZIE 2026-09-25: DirectAdmin nie ma natywnej obsługi serwera PostgreSQL (w CustomBuild tylko rozszerzenia PHP: php_pgsql, od 1.707 pdo_pgsql), więc serwer to PostgreSQL 16 z AppStream systemu (bez obcych repozytoriów, wg postgresql.org → Red Hat family), tylko localhost, hasła scram-sha-256, superużytkownik tylko przez peer. Panel → Bazy danych → „PostgreSQL”: do 5 baz na konto, baza i użytkownik <login>_<nazwa>, hasło generowane i pokazane raz, zmiana hasła, usuwanie z potwierdzeniem, rozmiar każdej bazy. Izolacja sprawdzona na prawdziwym PostgreSQL 16: brak CONNECT do cudzej bazy i do postgres, brak CREATE DATABASE, złe hasło odrzucone; hasło idzie do psql przez stdin. Kopia: codzienny pg_dump do ~/.verris-pgsql/ konta (zapis jako właściciel konta) — wchodzi do kopii DirectAdmina; usunięcie konta w DA usuwa bazy (hook user_destroy_post). Przy okazji: hasła z payloadu zadań węzła (też instalatory aplikacji i WordPressa) są usuwane po wykonaniu i maskowane w panelu administratora. D3 w wezel.csv. | 2026-10-02 D3: 02.10 t1: postgresql active, 5432 tylko 127.0.0.1 i [::1]; panel klienta → Bazy danych → PostgreSQL: utworzone ovsekucx_test1 i ovsekucx_test2 (hasło pokazane raz, rozmiar w panelu); pdo_pgsql włączone z panelu (d3 → PHP i serwer → rozszerzenia) → `php -m` konta: pdo_pgsql, pgsql; PDO na 127.0.0.1 → „OK: ovsekucx_test1”; izolacja: ovsekucx_test2 → własna baza weszło, ovsekucx_test1 i postgres „permission denied for database”; „Nowe hasło” → stare hasło odrzucone; verris-pgsql-dump → ~/.verris-pgsql/<baza>.dump (600, właściciel konta); hook DA user_destroy_post/verris-pgsql.sh na miejscu (samego usunięcia konta nie wykonywano); opcja CustomBuild natywnego PHP: php_pdo_pgsql (na t1 =no; strony działają na alt-php z selektora); usunięcie obu baz z panelu (potwierdzenie) → „Bazy: 0 z 5”. Poprawione po drodze: lista baz wychodziła poza kartę w wąskiej kolumnie (a38baf8).
A91: D-15 | B91: D | C91: Redis / cache obiektowy dla klienta | D91: CZĘŚĆ | E91: TAK | F91: CZĘŚĆ | G91: TAK | H91: TAK | I91: DZIAŁA | J91: ops/scripts/node-redis.sh (zadanie REDIS_ACCESS: instancja na konto, tylko gniazdo ~/.verris-redis/redis.sock 0700, konfiguracja roota, CONFIG wyłączone, 64 MB, MemoryMax w systemd), subscriptions/redis-access.service.ts, :id/hosting-redis, panel RedisPanel.tsx (PHP i serwer); WordPress: node-wp-update.sh WPU_CACHE=redis-on/off (wtyczka Redis Object Cache, WP_REDIS_PATH, kontrola strony), WpUpdatesPanel.tsx; testy redis-access.service.spec.ts, wp-update.service.spec.ts; D3 t1 (d3.hvln.pl) 29.09 po wdrożeniu 13:00 (panel klienta): Redis konta włączony z panelu → gniazdo ~/.verris-redis/redis.sock | K91: PARYTET | L91: — | M91: M | N91: 2026-09-24: KOD (D2) + skrypt sprawdzony lokalnie z prawdziwym redis-server (inny użytkownik → Permission denied, CONFIG SET → odrzucone). Wybór: własna instancja na konto (systemd verris-redis@) zamiast per-user Redis DA — testowalne bez węzła i limit pamięci pod naszą kontrolą. OTWARTE do D3 (sprint 21): redis-server z CustomBuild na węźle, gniazdo widoczne w klatce CageFS, PHP redis extension. | 3 z 5 hostingów PL ma w cenie — realny wyróżnik dla WordPressa
A92: D-16 | B92: D | C92: Memcached | D92: TAK | E92: TAK | F92: CZĘŚĆ | G92: CZĘŚĆ | H92: CZĘŚĆ | I92: DZIAŁA | J92: ops/scripts/node-memcached.sh (zadanie MEMCACHED_ACCESS, migracja 20260925201000); redis-access.service.ts (silnik memcached); services.controller.ts :id/hosting-memcached; client-panel RedisPanel silnik="memcached" (zakładka PHP i serwer); node-hosting-profile.sh (pakiet memcached, usługa TCP wyłączona) | K92: PARYTET | L92: NISKA | M92: M | N92: 2026-09-25 KOD (D2): tym samym torem co Redis (D-15) — instancja na konto jako klient (systemd verris-memcached@, MemoryMax), wyłącznie gniazdo UNIX ~/.verris-memcached/memcached.sock z maską 0700 (dokumentacja memcached, wiki ConfiguringServer: „-s <file> … TCP/UDP will be disabled”), 64 MB. Domyślna usługa memcached (port 11211) na węźle wyłączona. Test redis-access.service.spec.ts. D3 w wezel.csv. | 2026-09-30 D3 t1: 30.09 d3.hvln.pl: Memcached włączony z panelu → gniazdo w katalogu konta, set/get z PHP działa. Rozszerzenie memcached PHP nie było włączane (tak samo OPcache po zmianie wersji) → 8958de1; na d3 włączone z panelu. | 2026-10-01: werdykt PARYTET — działa na węźle (D3).
A93: D-17 | B93: D | C93: Podgląd rozmiaru bazy | D93: TAK | E93: TAK | F93: TAK | G93: TAK | H93: TAK | I93: DZIAŁA | J93: ops/scripts/node-db-transfer.sh (sizes); db-transfer.service.ts zlecRozmiary/rozmiaryZLogu; DbTransferPanel.tsx „Rozmiar baz”; D3 t1 (d3.hvln.pl) 29.09 po wdrożeniu (panel klienta): Przelicz rozmiary → 1008 KB · 14 tabel | K93: PARYTET | L93: — | M93: S | N93: 2026-09-24: KOD (D2) + skrypt sprawdzony lokalnie na MariaDB 10.11 — rozmiar (dane + indeksy) i liczba tabel każdej bazy konta z information_schema, przeliczane na żądanie; LIKE z ucieczką „_” (baza loginXnazwa nie wchodzi). Tylko odczyt — wg skali D2 wystarcza (PARYTET). Stan CZĘŚCIOWE do testu na węźle (wezel.csv).
A94: D-18 | B94: D | C94: Naprawa / optymalizacja tabel | D94: TAK | E94: TAK | F94: TAK | G94: CZĘŚĆ | H94: NIE | I94: DZIAŁA | J94: ops/scripts/node-db-transfer.sh (repair/optimize); db-transfer.service.ts zlecKonserwacje; DbTransferPanel.tsx; D3 t1 (d3.hvln.pl) 29.09 po wdrożeniu (panel klienta): Sprawdź i napraw oraz Optymalizuj → „Tabel: 14. Wszystkie w porządku” | K94: PARYTET | L94: — | M94: S | N94: 2026-09-24: KOD (D2) + skrypt sprawdzony lokalnie na MariaDB 10.11 — „Sprawdź i napraw” (mysqlcheck --check --auto-repair) i „Optymalizuj” (--optimize; InnoDB: recreate + analyze) na jednej bazie konta (prefiks loginu sprawdzany w API i w skrypcie, obca baza → odmowa). Wynik: liczba tabel i uwagi (naprawione/uszkodzone), bez szumu „already up to date”. OTWARTE do D3 (sprint 21).
A95: E-01 | B95: E | C95: Utworzenie skrzynki e-mail | D95: TAK | E95: TAK | F95: TAK | G95: TAK | H95: TAK | I95: DZIAŁA | J95: services.controller.ts:429 | K95: PARYTET | L95: — | M95: —
A96: E-02 | B96: E | C96: Zmiana hasła skrzynki | D96: TAK | E96: TAK | F96: TAK | G96: TAK | H96: TAK | I96: DZIAŁA | J96: services.controller.ts:438 | K96: PARYTET | L96: — | M96: —
A97: E-03 | B97: E | C97: Usunięcie skrzynki | D97: TAK | E97: TAK | F97: TAK | G97: TAK | H97: TAK | I97: DZIAŁA | J97: services.controller.ts:447 | K97: PARYTET | L97: — | M97: —
A98: E-04 | B98: E | C98: Ustawienie quoty przy tworzeniu skrzynki | D98: TAK | E98: TAK | F98: TAK | G98: TAK | H98: TAK | I98: DZIAŁA | J98: MailTab.tsx:139 | K98: PARYTET | L98: — | M98: —
A99: E-05 | B99: E | C99: Zmiana quoty ISTNIEJĄCEJ skrzynki | D99: TAK | E99: TAK | F99: TAK | G99: TAK | H99: TAK | I99: DZIAŁA | J99: 2026-09-23 D1: POST /services/:id/hosting-email/quota (ZmienRozmiarSkrzynkiDto 10–102400 MB) → directadmin.service changeHostingEmailQuota (CMD_API_POP action=modify bez passwd) + audyt HOSTING_EMAIL_QUOTA_CHANGED; UI MailTab — klik w rozmiar skrzynki; 29.09: lista pokazuje 1024 MB (type=quota) — zmiana rozmiaru do sprawdzenia; D3 t1 (d3.hvln.pl) 29.09 po wdrożeniu (panel klienta): FAIL: zmiana rozmiaru → „wymagane jest podanie nazwy użytkownika i domeny” (DA 1.710 wymaga pustych passwd/passwd2); poprawka 4b69d3b czeka na push; D3 t1 (d3.hvln.pl) 29.09 po wdrożeniu 13:00 (panel klienta): rozmiar skrzynki 1024 → 1500 → 1024 MB z panelu, DA potwierdza (4b69d3b) | K99: PARYTET | L99: — | M99: S | N99: brak jakiejkolwiek ścieżki edycji — klient musi usunąć i odtworzyć skrzynkę | KOD: zmiana rozmiaru bez usuwania skrzynki. Przy okazji body tworzenia skrzynki i zmiany hasła dostały klasy DTO (wcześniej interfejs = zero walidacji na granicy zaufania). OTWARTE do D3: czy DA przy modify bez passwd zostawia hasło (komentarz ponytail).
A100: E-06 | B100: E | C100: Podgląd zużycia skrzynki | D100: TAK | E100: TAK | F100: TAK | G100: TAK | H100: TAK | I100: DZIAŁA | J100: ops/scripts/node-disk-usage.sh (VERRIS_DU_SKRZYNKA: du ~/imap/<domena>/<login> jako klient), DiskUsageService.skrzynki, MailTab.tsx („X MB z Y MB” przy skrzynce + „Przelicz zajętość”); test disk-usage.service.spec.ts; D3 t1 29.09 (panel klienta, d3.hvln.pl): przy skrzynce „0,2 MB z 1024 MB” po „Przelicz zajętość” (zgodne z du imap) | K100: PARYTET | L100: ŚREDNIA | M100: S | N100: 2026-09-24: KOD (D2) + skrypt sprawdzony lokalnie — zajętość każdej skrzynki liczona z katalogu poczty konta (bez zgadywania formatu CMD_API_POP), z datą pomiaru i przeliczeniem na żądanie. OTWARTE do D3 (sprint 21): układ katalogów poczty DA (imap/<domena>/<login>/Maildir) na węźle. | | 2026-09-24 SKALA DOWODU (decyzja PM): funkcja bez pieniędzy, danych klienta i dostępu — D2 (test w CI) wystarcza do „zrobione”, więc werdykt PARYTET. Stan zostaje CZĘŚCIOWE do testu na węźle (audyt/dane/wezel.csv).
...
